{
"meta":{"test_sets":[],"test_metrics":[],"learn_metrics":[{"best_value":"Min","name":"Logloss"}],"launch_mode":"Train","parameters":"","iteration_count":1000,"learn_sets":["learn"],"name":"experiment"},
"iterations":[
{"learn":[0.6702433573],"iteration":0,"passed_time":0.01659025288,"remaining_time":16.57366263},
{"learn":[0.649449056],"iteration":1,"passed_time":0.02089141704,"remaining_time":10.4248171},
{"learn":[0.6307257894],"iteration":2,"passed_time":0.02477408955,"remaining_time":8.233255759},
{"learn":[0.6133442688],"iteration":3,"passed_time":0.02927274976,"remaining_time":7.28891469},
{"learn":[0.5984948781],"iteration":4,"passed_time":0.0338399926,"remaining_time":6.734158528},
{"learn":[0.5839116364],"iteration":5,"passed_time":0.03926280137,"remaining_time":6.504537428},
{"learn":[0.5708194529],"iteration":6,"passed_time":0.04396845746,"remaining_time":6.237239751},
{"learn":[0.5592621002],"iteration":7,"passed_time":0.04877819446,"remaining_time":6.048496113},
{"learn":[0.5485007884],"iteration":8,"passed_time":0.05374017843,"remaining_time":5.917390758},
{"learn":[0.5390984904],"iteration":9,"passed_time":0.06839226099,"remaining_time":6.770833838},
{"learn":[0.5303421987],"iteration":10,"passed_time":0.08110075735,"remaining_time":7.291695366},
{"learn":[0.5223825785],"iteration":11,"passed_time":0.1006306586,"remaining_time":8.285257555},
{"learn":[0.5147678782],"iteration":12,"passed_time":0.1111069495,"remaining_time":8.435581472},
{"learn":[0.5077506917],"iteration":13,"passed_time":0.1205915522,"remaining_time":8.493090746},
{"learn":[0.5016808319],"iteration":14,"passed_time":0.1313073383,"remaining_time":8.622515215},
{"learn":[0.4959132843],"iteration":15,"passed_time":0.143145935,"remaining_time":8.803475004},
{"learn":[0.490657191],"iteration":16,"passed_time":0.1523105021,"remaining_time":8.807130799},
{"learn":[0.4858058472],"iteration":17,"passed_time":0.1618242702,"remaining_time":8.828412965},
{"learn":[0.4812639974],"iteration":18,"passed_time":0.1733374154,"remaining_time":8.94968445},
{"learn":[0.4772892049],"iteration":19,"passed_time":0.18378129,"remaining_time":9.00528321},
{"learn":[0.4733886108],"iteration":20,"passed_time":0.1956373874,"remaining_time":9.120428678},
{"learn":[0.4699980418],"iteration":21,"passed_time":0.209983851,"remaining_time":9.334736651},
{"learn":[0.4669310659],"iteration":22,"passed_time":0.2213726237,"remaining_time":9.403524061},
{"learn":[0.4640531616],"iteration":23,"passed_time":0.2317577495,"remaining_time":9.424815145},
{"learn":[0.4615630493],"iteration":24,"passed_time":0.2429688587,"remaining_time":9.47578549},
{"learn":[0.4591876221],"iteration":25,"passed_time":0.254029471,"remaining_time":9.516334797},
{"learn":[0.4568469493],"iteration":26,"passed_time":0.2636606537,"remaining_time":9.501548744},
{"learn":[0.4545850932],"iteration":27,"passed_time":0.2730448824,"remaining_time":9.478558062},
{"learn":[0.4527285156],"iteration":28,"passed_time":0.2820384109,"remaining_time":9.443424035},
{"learn":[0.4508249156],"iteration":29,"passed_time":0.290554532,"remaining_time":9.394596534},
{"learn":[0.4490236003],"iteration":30,"passed_time":0.2996010184,"remaining_time":9.364947963},
{"learn":[0.4475473073],"iteration":31,"passed_time":0.3135946971,"remaining_time":9.486239588},
{"learn":[0.4460832265],"iteration":32,"passed_time":0.3239764479,"remaining_time":9.493491671},
{"learn":[0.4447540639],"iteration":33,"passed_time":0.3312560526,"remaining_time":9.411569025},
{"learn":[0.4432308044],"iteration":34,"passed_time":0.3364388242,"remaining_time":9.27609901},
{"learn":[0.4421321665],"iteration":35,"passed_time":0.3411828125,"remaining_time":9.136117535},
{"learn":[0.4410468394],"iteration":36,"passed_time":0.3461637541,"remaining_time":9.009613384},
{"learn":[0.4400229594],"iteration":37,"passed_time":0.351881848,"remaining_time":8.908166783},
{"learn":[0.4389216003],"iteration":38,"passed_time":0.357091869,"remaining_time":8.7991099},
{"learn":[0.4380255941],"iteration":39,"passed_time":0.36355624,"remaining_time":8.725349759},
{"learn":[0.4372489522],"iteration":40,"passed_time":0.3706465985,"remaining_time":8.669514339},
{"learn":[0.436334844],"iteration":41,"passed_time":0.3754726681,"remaining_time":8.564352764},
{"learn":[0.4356087596],"iteration":42,"passed_time":0.3805306922,"remaining_time":8.469020289},
{"learn":[0.4349111938],"iteration":43,"passed_time":0.3854707186,"remaining_time":8.375227431},
{"learn":[0.4342277018],"iteration":44,"passed_time":0.3901288756,"remaining_time":8.279401694},
{"learn":[0.4337011871],"iteration":45,"passed_time":0.3951533173,"remaining_time":8.19513619},
{"learn":[0.4332247569],"iteration":46,"passed_time":0.4030178684,"remaining_time":8.171830395},
{"learn":[0.4326969859],"iteration":47,"passed_time":0.408245847,"remaining_time":8.096875966},
{"learn":[0.4322139842],"iteration":48,"passed_time":0.4181374826,"remaining_time":8.11528053},
{"learn":[0.4316264648],"iteration":49,"passed_time":0.4351379763,"remaining_time":8.26762155},
{"learn":[0.4311023254],"iteration":50,"passed_time":0.4456406417,"remaining_time":8.292411156},
{"learn":[0.4306623179],"iteration":51,"passed_time":0.4573061589,"remaining_time":8.33704305},
{"learn":[0.4302962545],"iteration":52,"passed_time":0.4706012685,"remaining_time":8.408667949},
{"learn":[0.4298790741],"iteration":53,"passed_time":0.4820661647,"remaining_time":8.445085033},
{"learn":[0.4294894002],"iteration":54,"passed_time":0.4949301989,"remaining_time":8.503800691},
{"learn":[0.4290898844],"iteration":55,"passed_time":0.506700089,"remaining_time":8.541515787},
{"learn":[0.4287058716],"iteration":56,"passed_time":0.5212358409,"remaining_time":8.623252596},
{"learn":[0.4285286306],"iteration":57,"passed_time":0.5288193146,"remaining_time":8.588755075},
{"learn":[0.4281998851],"iteration":58,"passed_time":0.5406966185,"remaining_time":8.623652848},
{"learn":[0.4279341736],"iteration":59,"passed_time":0.5537730655,"remaining_time":8.675778027},
{"learn":[0.4276559245],"iteration":60,"passed_time":0.5648898027,"remaining_time":8.695598765},
{"learn":[0.4274017741],"iteration":61,"passed_time":0.5784960311,"remaining_time":8.752085116},
{"learn":[0.4271718648],"iteration":62,"passed_time":0.5898713871,"remaining_time":8.773166503},
{"learn":[0.4268930817],"iteration":63,"passed_time":0.6015392372,"remaining_time":8.797511344},
{"learn":[0.4266507517],"iteration":64,"passed_time":0.6130847988,"remaining_time":8.818989028},
{"learn":[0.4264016774],"iteration":65,"passed_time":0.6270932692,"remaining_time":8.8743199},
{"learn":[0.4261383413],"iteration":66,"passed_time":0.6389471576,"remaining_time":8.897577582},
{"learn":[0.4259433085],"iteration":67,"passed_time":0.6495151127,"remaining_time":8.902177721},
{"learn":[0.4257714233],"iteration":68,"passed_time":0.6596542433,"remaining_time":8.900552181},
{"learn":[0.4255152893],"iteration":69,"passed_time":0.6690349731,"remaining_time":8.888607499},
{"learn":[0.4253092906],"iteration":70,"passed_time":0.6776755086,"remaining_time":8.867049965},
{"learn":[0.4251396281],"iteration":71,"passed_time":0.6890847809,"remaining_time":8.881537176},
{"learn":[0.4249958852],"iteration":72,"passed_time":0.7071834197,"remaining_time":8.980260686},
{"learn":[0.4248677775],"iteration":73,"passed_time":0.7165622325,"remaining_time":8.96671118},
{"learn":[0.4245886434],"iteration":74,"passed_time":0.7284049131,"remaining_time":8.983660595},
{"learn":[0.424395167],"iteration":75,"passed_time":0.7382694243,"remaining_time":8.975801948},
{"learn":[0.4241888021],"iteration":76,"passed_time":0.7481436442,"remaining_time":8.968007579},
{"learn":[0.4239505412],"iteration":77,"passed_time":0.75652156,"remaining_time":8.942472799},
{"learn":[0.4236809845],"iteration":78,"passed_time":0.7671570137,"remaining_time":8.943691261},
{"learn":[0.4235682882],"iteration":79,"passed_time":0.7777276777,"remaining_time":8.943868294},
{"learn":[0.4233346965],"iteration":80,"passed_time":0.7872871959,"remaining_time":8.932307816},
{"learn":[0.4231591543],"iteration":81,"passed_time":0.7995488672,"remaining_time":8.951047074},
{"learn":[0.4229793752],"iteration":82,"passed_time":0.8109702233,"remaining_time":8.959755358},
{"learn":[0.4227427216],"iteration":83,"passed_time":0.8226928643,"remaining_time":8.971269806},
{"learn":[0.4225414886],"iteration":84,"passed_time":0.8384474249,"remaining_time":9.025639926},
{"learn":[0.4223169556],"iteration":85,"passed_time":0.8450853344,"remaining_time":8.981488321},
{"learn":[0.4221997782],"iteration":86,"passed_time":0.8497170749,"remaining_time":8.917145855},
{"learn":[0.4220674896],"iteration":87,"passed_time":0.855526834,"remaining_time":8.866369007},
{"learn":[0.4219514364],"iteration":88,"passed_time":0.8601094085,"remaining_time":8.804041249},
{"learn":[0.4218142395],"iteration":89,"passed_time":0.8647856902,"remaining_time":8.743944201},
{"learn":[0.421629425],"iteration":90,"passed_time":0.870255872,"remaining_time":8.692995469},
{"learn":[0.4214800161],"iteration":91,"passed_time":0.8772089412,"remaining_time":8.657670855},
{"learn":[0.421291158],"iteration":92,"passed_time":0.882531376,"remaining_time":8.607053312},
{"learn":[0.4211535645],"iteration":93,"passed_time":0.8881503889,"remaining_time":8.560258003},
{"learn":[0.4209910634],"iteration":94,"passed_time":0.89365307,"remaining_time":8.513221351},
{"learn":[0.4208176676],"iteration":95,"passed_time":0.8989333397,"remaining_time":8.464955615},
{"learn":[0.4207124074],"iteration":96,"passed_time":0.9041598193,"remaining_time":8.417075432},
{"learn":[0.4205958862],"iteration":97,"passed_time":0.9106947309,"remaining_time":8.382108646},
{"learn":[0.4204492137],"iteration":98,"passed_time":0.9162098288,"remaining_time":8.338434907},
{"learn":[0.4202528687],"iteration":99,"passed_time":0.9208988603,"remaining_time":8.288089742},
{"learn":[0.4200655772],"iteration":100,"passed_time":0.9257770129,"remaining_time":8.240332026},
{"learn":[0.4198652802],"iteration":101,"passed_time":0.9307145813,"remaining_time":8.193938177},
{"learn":[0.4197372945],"iteration":102,"passed_time":0.9359485599,"remaining_time":8.150930662},
{"learn":[0.4195879873],"iteration":103,"passed_time":0.9408721706,"remaining_time":8.105975624},
{"learn":[0.4194642131],"iteration":104,"passed_time":0.946414518,"remaining_time":8.067057082},
{"learn":[0.4193427327],"iteration":105,"passed_time":0.9514050854,"remaining_time":8.024114588},
{"learn":[0.4192434336],"iteration":106,"passed_time":0.956783603,"remaining_time":7.985119229},
{"learn":[0.4191153056],"iteration":107,"passed_time":0.9615183835,"remaining_time":7.941429612},
{"learn":[0.4189376882],"iteration":108,"passed_time":0.9663722027,"remaining_time":7.899427822},
{"learn":[0.4188315125],"iteration":109,"passed_time":0.9711386075,"remaining_time":7.857394188},
{"learn":[0.4186601308],"iteration":110,"passed_time":0.976178632,"remaining_time":7.818223458},
{"learn":[0.4185811717],"iteration":111,"passed_time":0.9817672284,"remaining_time":7.784011597},
{"learn":[0.418479894],"iteration":112,"passed_time":0.9872124527,"remaining_time":7.749180934},
{"learn":[0.4183565725],"iteration":113,"passed_time":0.992009774,"remaining_time":7.709830349},
{"learn":[0.4182394002],"iteration":114,"passed_time":0.9965111841,"remaining_time":7.668803461},
{"learn":[0.4181218872],"iteration":115,"passed_time":1.001268339,"remaining_time":7.630355275},
{"learn":[0.4180596161],"iteration":116,"passed_time":1.006600441,"remaining_time":7.59682213},
{"learn":[0.4179395955],"iteration":117,"passed_time":1.012136872,"remaining_time":7.565294249},
{"learn":[0.4178045553],"iteration":118,"passed_time":1.018624909,"remaining_time":7.541248274},
{"learn":[0.417720342],"iteration":119,"passed_time":1.023986594,"remaining_time":7.509235021},
{"learn":[0.4176511841],"iteration":120,"passed_time":1.02877679,"remaining_time":7.473510732},
{"learn":[0.4175222015],"iteration":121,"passed_time":1.034519093,"remaining_time":7.445145601},
{"learn":[0.4174272461],"iteration":122,"passed_time":1.042277855,"remaining_time":7.431525842},
{"learn":[0.4172861226],"iteration":123,"passed_time":1.04767783,"remaining_time":7.401336928},
{"learn":[0.4171791331],"iteration":124,"passed_time":1.053805624,"remaining_time":7.376639365},
{"learn":[0.4170555166],"iteration":125,"passed_time":1.058642361,"remaining_time":7.34328114},
{"learn":[0.4169401398],"iteration":126,"passed_time":1.06345289,"remaining_time":7.310191914},
{"learn":[0.4168305562],"iteration":127,"passed_time":1.068260002,"remaining_time":7.277521265},
{"learn":[0.4167114105],"iteration":128,"passed_time":1.073342776,"remaining_time":7.247143858},
{"learn":[0.4165895538],"iteration":129,"passed_time":1.078626212,"remaining_time":7.218498497},
{"learn":[0.4165152079],"iteration":130,"passed_time":1.083645279,"remaining_time":7.188456088},
{"learn":[0.4164440715],"iteration":131,"passed_time":1.088657763,"remaining_time":7.158749533},
{"learn":[0.4163189494],"iteration":132,"passed_time":1.093179798,"remaining_time":7.126217178},
{"learn":[0.4162172343],"iteration":133,"passed_time":1.099163887,"remaining_time":7.10355169},
{"learn":[0.4161100566],"iteration":134,"passed_time":1.104154038,"remaining_time":7.07476476},
{"learn":[0.4159914246],"iteration":135,"passed_time":1.109624887,"remaining_time":7.049381632},
{"learn":[0.4158518117],"iteration":136,"passed_time":1.114771617,"remaining_time":7.022247484},
{"learn":[0.4157124278],"iteration":137,"passed_time":1.121055033,"remaining_time":7.002532165},
{"learn":[0.4156038818],"iteration":138,"passed_time":1.130648592,"remaining_time":7.00351394},
{"learn":[0.4155088552],"iteration":139,"passed_time":1.13684926,"remaining_time":6.983502598},
{"learn":[0.415375885],"iteration":140,"passed_time":1.142107946,"remaining_time":6.95794841},
{"learn":[0.4153171285],"iteration":141,"passed_time":1.146957599,"remaining_time":6.930208594},
{"learn":[0.4151777242],"iteration":142,"passed_time":1.15211658,"remaining_time":6.904642724},
{"learn":[0.41511291],"iteration":143,"passed_time":1.158546411,"remaining_time":6.886914777},
{"learn":[0.414979009],"iteration":144,"passed_time":1.164698413,"remaining_time":6.867704438},
{"learn":[0.4148668009],"iteration":145,"passed_time":1.17003464,"remaining_time":6.84390125},
{"learn":[0.4148173319],"iteration":146,"passed_time":1.174620715,"remaining_time":6.815996396},
{"learn":[0.4146119843],"iteration":147,"passed_time":1.180306686,"remaining_time":6.794738489},
{"learn":[0.4144516246],"iteration":148,"passed_time":1.185579873,"remaining_time":6.771332024},
{"learn":[0.4143116252],"iteration":149,"passed_time":1.190699895,"remaining_time":6.747299407},
{"learn":[0.4142277883],"iteration":150,"passed_time":1.196368657,"remaining_time":6.726602583},
{"learn":[0.4141542867],"iteration":151,"passed_time":1.201641885,"remaining_time":6.703896832},
{"learn":[0.4140749563],"iteration":152,"passed_time":1.206619494,"remaining_time":6.679782426},
{"learn":[0.4139680278],"iteration":153,"passed_time":1.212264298,"remaining_time":6.659581793},
{"learn":[0.4138371989],"iteration":154,"passed_time":1.218860874,"remaining_time":6.64475767},
{"learn":[0.4137700907],"iteration":155,"passed_time":1.224036896,"remaining_time":6.622353463},
{"learn":[0.4136654917],"iteration":156,"passed_time":1.229036213,"remaining_time":6.599219922},
{"learn":[0.4135202688],"iteration":157,"passed_time":1.234985803,"remaining_time":6.581380036},
{"learn":[0.4133588511],"iteration":158,"passed_time":1.241862123,"remaining_time":6.568591482},
{"learn":[0.4132548981],"iteration":159,"passed_time":1.247899962,"remaining_time":6.551474799},
{"learn":[0.413124705],"iteration":160,"passed_time":1.253202648,"remaining_time":6.530664731},
{"learn":[0.4130384776],"iteration":161,"passed_time":1.257842972,"remaining_time":6.50661982},
{"learn":[0.4129520772],"iteration":162,"passed_time":1.263244324,"remaining_time":6.486720852},
{"learn":[0.4128562775],"iteration":163,"passed_time":1.268778379,"remaining_time":6.467675152},
{"learn":[0.4127917582],"iteration":164,"passed_time":1.273807904,"remaining_time":6.446239998},
{"learn":[0.4126507416],"iteration":165,"passed_time":1.27952754,"remaining_time":6.428469687},
{"learn":[0.4125495809],"iteration":166,"passed_time":1.284424567,"remaining_time":6.406740504},
{"learn":[0.4124678548],"iteration":167,"passed_time":1.289546507,"remaining_time":6.386325557},
{"learn":[0.4123203888],"iteration":168,"passed_time":1.294383701,"remaining_time":6.364691453},
{"learn":[0.4122172089],"iteration":169,"passed_time":1.299736344,"remaining_time":6.345771563},
{"learn":[0.4121157379],"iteration":170,"passed_time":1.304425917,"remaining_time":6.323795818},
{"learn":[0.4119987996],"iteration":171,"passed_time":1.309210571,"remaining_time":6.302478796},
{"learn":[0.4119453735],"iteration":172,"passed_time":1.313569067,"remaining_time":6.279315714},
{"learn":[0.4118504639],"iteration":173,"passed_time":1.318500094,"remaining_time":6.259086652},
{"learn":[0.4117033997],"iteration":174,"passed_time":1.32328829,"remaining_time":6.238359082},
{"learn":[0.4115678507],"iteration":175,"passed_time":1.328686223,"remaining_time":6.220667319},
{"learn":[0.411438914],"iteration":176,"passed_time":1.333717665,"remaining_time":6.201410386},
{"learn":[0.4113486633],"iteration":177,"passed_time":1.338291866,"remaining_time":6.180201762},
{"learn":[0.4112565867],"iteration":178,"passed_time":1.343303849,"remaining_time":6.161186926},
{"learn":[0.4111831207],"iteration":179,"passed_time":1.347351934,"remaining_time":6.137936588},
{"learn":[0.4110985667],"iteration":180,"passed_time":1.352763076,"remaining_time":6.121066073},
{"learn":[0.4109870148],"iteration":181,"passed_time":1.357600354,"remaining_time":6.101742252},
{"learn":[0.4108458405],"iteration":182,"passed_time":1.362893707,"remaining_time":6.084612887},
{"learn":[0.4107302755],"iteration":183,"passed_time":1.367730027,"remaining_time":6.065585338},
{"learn":[0.4106334279],"iteration":184,"passed_time":1.373009963,"remaining_time":6.048665512},
{"learn":[0.4105454407],"iteration":185,"passed_time":1.378435355,"remaining_time":6.032507412},
{"learn":[0.4104547119],"iteration":186,"passed_time":1.383265591,"remaining_time":6.013876607},
{"learn":[0.4103046061],"iteration":187,"passed_time":1.388321281,"remaining_time":5.996366385},
{"learn":[0.4102148641],"iteration":188,"passed_time":1.393045479,"remaining_time":5.977565521},
{"learn":[0.4101229146],"iteration":189,"passed_time":1.398183626,"remaining_time":5.960677565},
{"learn":[0.4100567118],"iteration":190,"passed_time":1.402943448,"remaining_time":5.942310208},
{"learn":[0.4099141337],"iteration":191,"passed_time":1.407310111,"remaining_time":5.922430051},
{"learn":[0.4098636475],"iteration":192,"passed_time":1.412271137,"remaining_time":5.905195895},
{"learn":[0.4097644958],"iteration":193,"passed_time":1.417527074,"remaining_time":5.889313515},
{"learn":[0.409676295],"iteration":194,"passed_time":1.422206231,"remaining_time":5.871159056},
{"learn":[0.4095777283],"iteration":195,"passed_time":1.427724413,"remaining_time":5.856583816},
{"learn":[0.4095234985],"iteration":196,"passed_time":1.43298185,"remaining_time":5.841037693},
{"learn":[0.4094707743],"iteration":197,"passed_time":1.437886419,"remaining_time":5.824166202},
{"learn":[0.4093746694],"iteration":198,"passed_time":1.443252728,"remaining_time":5.809273543},
{"learn":[0.4092627157],"iteration":199,"passed_time":1.448755826,"remaining_time":5.795023304},
{"learn":[0.4091826833],"iteration":200,"passed_time":1.453529314,"remaining_time":5.777959809},
{"learn":[0.4091133118],"iteration":201,"passed_time":1.459428446,"remaining_time":5.765464851},
{"learn":[0.409003835],"iteration":202,"passed_time":1.464324681,"remaining_time":5.749097394},
{"learn":[0.4089404348],"iteration":203,"passed_time":1.469255917,"remaining_time":5.73297897},
{"learn":[0.4088380483],"iteration":204,"passed_time":1.473827576,"remaining_time":5.715575232},
{"learn":[0.4087438812],"iteration":205,"passed_time":1.47898164,"remaining_time":5.700540883},
{"learn":[0.4086403147],"iteration":206,"passed_time":1.483886917,"remaining_time":5.684648913},
{"learn":[0.4085496114],"iteration":207,"passed_time":1.488704113,"remaining_time":5.668527198},
{"learn":[0.40841834],"iteration":208,"passed_time":1.493581348,"remaining_time":5.652740893},
{"learn":[0.4082966156],"iteration":209,"passed_time":1.498515791,"remaining_time":5.63727369},
{"learn":[0.4082184397],"iteration":210,"passed_time":1.503295987,"remaining_time":5.621329546},
{"learn":[0.4081435293],"iteration":211,"passed_time":1.508364427,"remaining_time":5.606562117},
{"learn":[0.4080922597],"iteration":212,"passed_time":1.512473595,"remaining_time":5.588341406},
{"learn":[0.4080267232],"iteration":213,"passed_time":1.516980047,"remaining_time":5.571711763},
{"learn":[0.4079235128],"iteration":214,"passed_time":1.522004489,"remaining_time":5.557086158},
{"learn":[0.4077922312],"iteration":215,"passed_time":1.526850809,"remaining_time":5.541902938},
{"learn":[0.4077468465],"iteration":216,"passed_time":1.532283992,"remaining_time":5.528932561},
{"learn":[0.4076598002],"iteration":217,"passed_time":1.537528803,"remaining_time":5.515355615},
{"learn":[0.4075773315],"iteration":218,"passed_time":1.541913424,"remaining_time":5.498787141},
{"learn":[0.4074993032],"iteration":219,"passed_time":1.546842783,"remaining_time":5.484260777},
{"learn":[0.4074411469],"iteration":220,"passed_time":1.553326071,"remaining_time":5.475298685},
{"learn":[0.4073242137],"iteration":221,"passed_time":1.571758995,"remaining_time":5.508236478},
{"learn":[0.407243103],"iteration":222,"passed_time":1.584821442,"remaining_time":5.522001169},
{"learn":[0.4071154327],"iteration":223,"passed_time":1.592937197,"remaining_time":5.518389577},
{"learn":[0.4070371145],"iteration":224,"passed_time":1.599909224,"remaining_time":5.510798439},
{"learn":[0.4069758606],"iteration":225,"passed_time":1.604981456,"remaining_time":5.496706402},
{"learn":[0.406926005],"iteration":226,"passed_time":1.609111541,"remaining_time":5.479485554},
{"learn":[0.4068618113],"iteration":227,"passed_time":1.61748254,"remaining_time":5.476739128},
{"learn":[0.4068100586],"iteration":228,"passed_time":1.62327055,"remaining_time":5.465247136},
{"learn":[0.4067249196],"iteration":229,"passed_time":1.630917605,"remaining_time":5.460028505},
{"learn":[0.4066536662],"iteration":230,"passed_time":1.637208022,"remaining_time":5.450272592},
{"learn":[0.40658697],"iteration":231,"passed_time":1.644170967,"remaining_time":5.442772856},
{"learn":[0.4065039266],"iteration":232,"passed_time":1.649258198,"remaining_time":5.429103168},
{"learn":[0.4064151459],"iteration":233,"passed_time":1.655097373,"remaining_time":5.417968323},
{"learn":[0.4063643341],"iteration":234,"passed_time":1.661321374,"remaining_time":5.40813128},
{"learn":[0.4062263997],"iteration":235,"passed_time":1.666074279,"remaining_time":5.393562495},
{"learn":[0.4061425425],"iteration":236,"passed_time":1.67124505,"remaining_time":5.380421829},
{"learn":[0.406049413],"iteration":237,"passed_time":1.675838667,"remaining_time":5.365500269},
{"learn":[0.40589416],"iteration":238,"passed_time":1.680245954,"remaining_time":5.350071845},
{"learn":[0.4057920787],"iteration":239,"passed_time":1.695269862,"remaining_time":5.368354563},
{"learn":[0.405705541],"iteration":240,"passed_time":1.703701361,"remaining_time":5.365598891},
{"learn":[0.4056092784],"iteration":241,"passed_time":1.708307435,"remaining_time":5.350814197},
{"learn":[0.4055108999],"iteration":242,"passed_time":1.71372591,"remaining_time":5.338644089},
{"learn":[0.405372935],"iteration":243,"passed_time":1.718291153,"remaining_time":5.323885702},
{"learn":[0.4052419281],"iteration":244,"passed_time":1.722612149,"remaining_time":5.308457848},
{"learn":[0.4051104635],"iteration":245,"passed_time":1.728196371,"remaining_time":5.296992128},
{"learn":[0.4050311941],"iteration":246,"passed_time":1.733477598,"remaining_time":5.28465033},
{"learn":[0.4048931325],"iteration":247,"passed_time":1.73943298,"remaining_time":5.27440968},
{"learn":[0.4047979431],"iteration":248,"passed_time":1.744187385,"remaining_time":5.260581228},
{"learn":[0.4046499685],"iteration":249,"passed_time":1.749362073,"remaining_time":5.24808622},
{"learn":[0.404540273],"iteration":250,"passed_time":1.754551178,"remaining_time":5.235692558},
{"learn":[0.404419047],"iteration":251,"passed_time":1.759603618,"remaining_time":5.222950422},
{"learn":[0.4042724813],"iteration":252,"passed_time":1.764212692,"remaining_time":5.208960004},
{"learn":[0.4041377869],"iteration":253,"passed_time":1.769898162,"remaining_time":5.198204837},
{"learn":[0.4040034892],"iteration":254,"passed_time":1.775880834,"remaining_time":5.188357731},
{"learn":[0.4039101613],"iteration":255,"passed_time":1.781838715,"remaining_time":5.178468766},
{"learn":[0.4037722931],"iteration":256,"passed_time":1.786714368,"remaining_time":5.165481616},
{"learn":[0.4037012685],"iteration":257,"passed_time":1.790617249,"remaining_time":5.149759685},
{"learn":[0.4035738475],"iteration":258,"passed_time":1.795176908,"remaining_time":5.136008065},
{"learn":[0.4034363658],"iteration":259,"passed_time":1.79982744,"remaining_time":5.122585791},
{"learn":[0.4033265279],"iteration":260,"passed_time":1.804597595,"remaining_time":5.109569436},
{"learn":[0.4032639618],"iteration":261,"passed_time":1.809236627,"remaining_time":5.096246683},
{"learn":[0.4031454875],"iteration":262,"passed_time":1.814027782,"remaining_time":5.083416255},
{"learn":[0.4030485382],"iteration":263,"passed_time":1.818420819,"remaining_time":5.069536829},
{"learn":[0.4029700063],"iteration":264,"passed_time":1.823271556,"remaining_time":5.056998467},
{"learn":[0.402868337],"iteration":265,"passed_time":1.828711323,"remaining_time":5.046143274},
{"learn":[0.4027720693],"iteration":266,"passed_time":1.833475395,"remaining_time":5.033473649},
{"learn":[0.4026850179],"iteration":267,"passed_time":1.854366562,"remaining_time":5.064911653},
{"learn":[0.4025700887],"iteration":268,"passed_time":1.863572962,"remaining_time":5.064207566},
{"learn":[0.4025075582],"iteration":269,"passed_time":1.867942666,"remaining_time":5.050363504},
{"learn":[0.4024069875],"iteration":270,"passed_time":1.872219038,"remaining_time":5.036338299},
{"learn":[0.4022931875],"iteration":271,"passed_time":1.876913695,"remaining_time":5.0235043},
{"learn":[0.4022230428],"iteration":272,"passed_time":1.882510458,"remaining_time":5.013132245},
{"learn":[0.4020934906],"iteration":273,"passed_time":1.886931662,"remaining_time":4.999680242},
{"learn":[0.4020230001],"iteration":274,"passed_time":1.891325865,"remaining_time":4.986222735},
{"learn":[0.4019548442],"iteration":275,"passed_time":1.895951981,"remaining_time":4.973439254},
{"learn":[0.4018670095],"iteration":276,"passed_time":1.9008623,"remaining_time":4.961456472},
{"learn":[0.4017916056],"iteration":277,"passed_time":1.905134173,"remaining_time":4.94786645},
{"learn":[0.4016948497],"iteration":278,"passed_time":1.909077387,"remaining_time":4.933493892},
{"learn":[0.4015311635],"iteration":279,"passed_time":1.914191452,"remaining_time":4.92220659},
{"learn":[0.401428421],"iteration":280,"passed_time":1.920348246,"remaining_time":4.913631277},
{"learn":[0.4013147888],"iteration":281,"passed_time":1.925130525,"remaining_time":4.901573465},
{"learn":[0.4011946767],"iteration":282,"passed_time":1.929202861,"remaining_time":4.887768379},
{"learn":[0.4010887349],"iteration":283,"passed_time":1.932991493,"remaining_time":4.873316582},
{"learn":[0.401014801],"iteration":284,"passed_time":1.937330324,"remaining_time":4.860319935},
{"learn":[0.4008786418],"iteration":285,"passed_time":1.942063687,"remaining_time":4.848368786},
{"learn":[0.4008043722],"iteration":286,"passed_time":1.947105045,"remaining_time":4.83723309},
{"learn":[0.4007104797],"iteration":287,"passed_time":1.951423792,"remaining_time":4.824353262},
{"learn":[0.4005641886],"iteration":288,"passed_time":1.956856933,"remaining_time":4.814274323},
{"learn":[0.4004526978],"iteration":289,"passed_time":1.961260345,"remaining_time":4.801706362},
{"learn":[0.400377121],"iteration":290,"passed_time":1.966877025,"remaining_time":4.792150553},
{"learn":[0.4002693837],"iteration":291,"passed_time":1.972085504,"remaining_time":4.781631976},
{"learn":[0.4001977234],"iteration":292,"passed_time":1.977513646,"remaining_time":4.771679685},
{"learn":[0.4000953979],"iteration":293,"passed_time":1.983040786,"remaining_time":4.7619959},
{"learn":[0.3999960632],"iteration":294,"passed_time":1.987827106,"remaining_time":4.750569863},
{"learn":[0.39987323],"iteration":295,"passed_time":1.992977878,"remaining_time":4.740055494},
{"learn":[0.39976946],"iteration":296,"passed_time":1.998580558,"remaining_time":4.730646911},
{"learn":[0.3996643066],"iteration":297,"passed_time":2.003889994,"remaining_time":4.720573074},
{"learn":[0.3995661875],"iteration":298,"passed_time":2.008979102,"remaining_time":4.71001455},
{"learn":[0.3994705912],"iteration":299,"passed_time":2.014543074,"remaining_time":4.700600505},
{"learn":[0.3993811188],"iteration":300,"passed_time":2.01965568,"remaining_time":4.690163854},
{"learn":[0.3992854411],"iteration":301,"passed_time":2.024537207,"remaining_time":4.67922838},
{"learn":[0.3992233785],"iteration":302,"passed_time":2.029490025,"remaining_time":4.668496857},
{"learn":[0.3991578979],"iteration":303,"passed_time":2.037184664,"remaining_time":4.664080678},
{"learn":[0.3990355174],"iteration":304,"passed_time":2.042095858,"remaining_time":4.653300397},
{"learn":[0.3989409078],"iteration":305,"passed_time":2.050078741,"remaining_time":4.649524987},
{"learn":[0.3987889557],"iteration":306,"passed_time":2.055947332,"remaining_time":4.640949516},
{"learn":[0.3986463013],"iteration":307,"passed_time":2.060618072,"remaining_time":4.629700344},
{"learn":[0.3985171509],"iteration":308,"passed_time":2.066464289,"remaining_time":4.621122406},
{"learn":[0.3984287262],"iteration":309,"passed_time":2.071602186,"remaining_time":4.610985511},
{"learn":[0.3983194529],"iteration":310,"passed_time":2.077180492,"remaining_time":4.601856459},
{"learn":[0.3981582031],"iteration":311,"passed_time":2.082245058,"remaining_time":4.591617306},
{"learn":[0.3981101634],"iteration":312,"passed_time":2.087011879,"remaining_time":4.580757703},
{"learn":[0.398025533],"iteration":313,"passed_time":2.091672494,"remaining_time":4.569704876},
{"learn":[0.3978993988],"iteration":314,"passed_time":2.096424567,"remaining_time":4.558891518},
{"learn":[0.3977964172],"iteration":315,"passed_time":2.102395489,"remaining_time":4.550754793},
{"learn":[0.3976719411],"iteration":316,"passed_time":2.107443847,"remaining_time":4.540643998},
{"learn":[0.3975811768],"iteration":317,"passed_time":2.112744782,"remaining_time":4.531106733},
{"learn":[0.3974676005],"iteration":318,"passed_time":2.117643142,"remaining_time":4.520736614},
{"learn":[0.3973612213],"iteration":319,"passed_time":2.122774248,"remaining_time":4.510895276},
{"learn":[0.3972078908],"iteration":320,"passed_time":2.127921311,"remaining_time":4.501117041},
{"learn":[0.3971328786],"iteration":321,"passed_time":2.13283213,"remaining_time":4.490870137},
{"learn":[0.3970130208],"iteration":322,"passed_time":2.137270124,"remaining_time":4.479665245},
{"learn":[0.3969161174],"iteration":323,"passed_time":2.142187151,"remaining_time":4.469501587},
{"learn":[0.3968368276],"iteration":324,"passed_time":2.147306215,"remaining_time":4.459789831},
{"learn":[0.396734314],"iteration":325,"passed_time":2.152135161,"remaining_time":4.449506436},
{"learn":[0.3965922597],"iteration":326,"passed_time":2.157079521,"remaining_time":4.439493938},
{"learn":[0.3965328878],"iteration":327,"passed_time":2.161510766,"remaining_time":4.428461081},
{"learn":[0.3963759816],"iteration":328,"passed_time":2.166284962,"remaining_time":4.418167811},
{"learn":[0.396233607],"iteration":329,"passed_time":2.170909828,"remaining_time":4.407604802},
{"learn":[0.396105957],"iteration":330,"passed_time":2.176549256,"remaining_time":4.399128255},
{"learn":[0.3959763082],"iteration":331,"passed_time":2.182148812,"remaining_time":4.390588573},
{"learn":[0.3959027252],"iteration":332,"passed_time":2.187592328,"remaining_time":4.381754002},
{"learn":[0.3957953389],"iteration":333,"passed_time":2.193663874,"remaining_time":4.374192036},
{"learn":[0.3956658885],"iteration":334,"passed_time":2.198611108,"remaining_time":4.364407125},
{"learn":[0.3955255025],"iteration":335,"passed_time":2.204109456,"remaining_time":4.355740116},
{"learn":[0.3954345907],"iteration":336,"passed_time":2.208752114,"remaining_time":4.345408461},
{"learn":[0.3952987366],"iteration":337,"passed_time":2.214448584,"remaining_time":4.337174446},
{"learn":[0.3952355296],"iteration":338,"passed_time":2.219325153,"remaining_time":4.327356714},
{"learn":[0.3951556702],"iteration":339,"passed_time":2.224257054,"remaining_time":4.317675458},
{"learn":[0.3950175883],"iteration":340,"passed_time":2.230034731,"remaining_time":4.309656562},
{"learn":[0.3949010111],"iteration":341,"passed_time":2.235397499,"remaining_time":4.300852498},
{"learn":[0.3947619985],"iteration":342,"passed_time":2.240508397,"remaining_time":4.291586055},
{"learn":[0.3946722463],"iteration":343,"passed_time":2.24677373,"remaining_time":4.284545252},
{"learn":[0.3945943502],"iteration":344,"passed_time":2.252537198,"remaining_time":4.276556129},
{"learn":[0.3944835917],"iteration":345,"passed_time":2.257910466,"remaining_time":4.267842325},
{"learn":[0.3944330241],"iteration":346,"passed_time":2.262726327,"remaining_time":4.258098824},
{"learn":[0.3943282013],"iteration":347,"passed_time":2.267493648,"remaining_time":4.248292697},
{"learn":[0.394188797],"iteration":348,"passed_time":2.272517631,"remaining_time":4.238994206},
{"learn":[0.3940606486],"iteration":349,"passed_time":2.277750402,"remaining_time":4.230107889},
{"learn":[0.3939432678],"iteration":350,"passed_time":2.282495099,"remaining_time":4.220339941},
{"learn":[0.3938105723],"iteration":351,"passed_time":2.287685204,"remaining_time":4.21142049},
{"learn":[0.3937169088],"iteration":352,"passed_time":2.292697145,"remaining_time":4.202195617},
{"learn":[0.3936433156],"iteration":353,"passed_time":2.297925083,"remaining_time":4.193388711},
{"learn":[0.3935441895],"iteration":354,"passed_time":2.302786028,"remaining_time":4.183935177},
{"learn":[0.3934586589],"iteration":355,"passed_time":2.30779472,"remaining_time":4.174774718},
{"learn":[0.393359197],"iteration":356,"passed_time":2.313316068,"remaining_time":4.166560873},
{"learn":[0.3933137868],"iteration":357,"passed_time":2.318755959,"remaining_time":4.158215994},
{"learn":[0.3931858877],"iteration":358,"passed_time":2.323741818,"remaining_time":4.149076616},
{"learn":[0.3930783081],"iteration":359,"passed_time":2.328414224,"remaining_time":4.139403066},
{"learn":[0.3929487254],"iteration":360,"passed_time":2.333113964,"remaining_time":4.129805603},
{"learn":[0.39278803],"iteration":361,"passed_time":2.338791058,"remaining_time":4.121957721},
{"learn":[0.3926724854],"iteration":362,"passed_time":2.343839666,"remaining_time":4.113018917},
{"learn":[0.3925718028],"iteration":363,"passed_time":2.348980563,"remaining_time":4.104262742},
{"learn":[0.3924643402],"iteration":364,"passed_time":2.353309144,"remaining_time":4.094113167},
{"learn":[0.392354365],"iteration":365,"passed_time":2.376505348,"remaining_time":4.116678662},
{"learn":[0.3922643229],"iteration":366,"passed_time":2.390591983,"remaining_time":4.123282631},
{"learn":[0.3922215932],"iteration":367,"passed_time":2.403213024,"remaining_time":4.127257149},
{"learn":[0.3921344096],"iteration":368,"passed_time":2.413229407,"remaining_time":4.126687684},
{"learn":[0.3920075022],"iteration":369,"passed_time":2.427031881,"remaining_time":4.132513744},
{"learn":[0.3918760732],"iteration":370,"passed_time":2.438058327,"remaining_time":4.13352746},
{"learn":[0.3917501831],"iteration":371,"passed_time":2.452515955,"remaining_time":4.140268871},
{"learn":[0.3916879374],"iteration":372,"passed_time":2.464286263,"remaining_time":4.142379321},
{"learn":[0.3915690155],"iteration":373,"passed_time":2.47718463,"remaining_time":4.146303686},
{"learn":[0.3914563293],"iteration":374,"passed_time":2.489208973,"remaining_time":4.148681622},
{"learn":[0.3913706665],"iteration":375,"passed_time":2.499495851,"remaining_time":4.148099497},
{"learn":[0.3912862854],"iteration":376,"passed_time":2.512468842,"remaining_time":4.151904744},
{"learn":[0.3912083893],"iteration":377,"passed_time":2.523561788,"remaining_time":4.152527597},
{"learn":[0.3911747182],"iteration":378,"passed_time":2.533294177,"remaining_time":4.150859325},
{"learn":[0.3910996602],"iteration":379,"passed_time":2.541982796,"remaining_time":4.147445614},
{"learn":[0.390927592],"iteration":380,"passed_time":2.553577856,"remaining_time":4.148726229},
{"learn":[0.3908445333],"iteration":381,"passed_time":2.563108749,"remaining_time":4.146600018},
{"learn":[0.3907704875],"iteration":382,"passed_time":2.573130674,"remaining_time":4.145226178},
{"learn":[0.3906770325],"iteration":383,"passed_time":2.58306356,"remaining_time":4.143664461},
{"learn":[0.3905683034],"iteration":384,"passed_time":2.595636892,"remaining_time":4.146277113},
{"learn":[0.3904883575],"iteration":385,"passed_time":2.60768186,"remaining_time":4.147970626},
{"learn":[0.390438619],"iteration":386,"passed_time":2.619595789,"remaining_time":4.149385578},
{"learn":[0.3903555247],"iteration":387,"passed_time":2.631548716,"remaining_time":4.150793336},
{"learn":[0.3902569784],"iteration":388,"passed_time":2.642002925,"remaining_time":4.149778373},
{"learn":[0.3901601257],"iteration":389,"passed_time":2.655495614,"remaining_time":4.153467499},
{"learn":[0.3900603994],"iteration":390,"passed_time":2.665382167,"remaining_time":4.15145202},
{"learn":[0.3899184774],"iteration":391,"passed_time":2.676220701,"remaining_time":4.150872924},
{"learn":[0.3898213399],"iteration":392,"passed_time":2.687104066,"remaining_time":4.150310861},
{"learn":[0.3897366892],"iteration":393,"passed_time":2.702183266,"remaining_time":4.156149896},
{"learn":[0.3896781769],"iteration":394,"passed_time":2.714809056,"remaining_time":4.158125262},
{"learn":[0.3895394999],"iteration":395,"passed_time":2.728299036,"remaining_time":4.161344995},
{"learn":[0.3894711304],"iteration":396,"passed_time":2.739952762,"remaining_time":4.161691474},
{"learn":[0.3894036407],"iteration":397,"passed_time":2.752474929,"remaining_time":4.163291224},
{"learn":[0.3893574422],"iteration":398,"passed_time":2.765644458,"remaining_time":4.165795286},
{"learn":[0.3893213857],"iteration":399,"passed_time":2.777464555,"remaining_time":4.166196833},
{"learn":[0.3892207642],"iteration":400,"passed_time":2.791109033,"remaining_time":4.16926262},
{"learn":[0.3891256866],"iteration":401,"passed_time":2.802929005,"remaining_time":4.169531206},
{"learn":[0.3890456441],"iteration":402,"passed_time":2.8161612,"remaining_time":4.171831852},
{"learn":[0.388876653],"iteration":403,"passed_time":2.82929777,"remaining_time":4.173914533},
{"learn":[0.3888246663],"iteration":404,"passed_time":2.838604252,"remaining_time":4.170295135},
{"learn":[0.3886786397],"iteration":405,"passed_time":2.851519744,"remaining_time":4.171927901},
{"learn":[0.3885302175],"iteration":406,"passed_time":2.863178803,"remaining_time":4.171658551},
{"learn":[0.3884218597],"iteration":407,"passed_time":2.867781086,"remaining_time":4.161094125},
{"learn":[0.388277298],"iteration":408,"passed_time":2.872588865,"remaining_time":4.150855793},
{"learn":[0.3881940918],"iteration":409,"passed_time":2.877426436,"remaining_time":4.140686822},
{"learn":[0.388140976],"iteration":410,"passed_time":2.882584875,"remaining_time":4.131003629},
{"learn":[0.3879945984],"iteration":411,"passed_time":2.887446694,"remaining_time":4.120919068},
{"learn":[0.3879420573],"iteration":412,"passed_time":2.892011645,"remaining_time":4.110437858},
{"learn":[0.3878378194],"iteration":413,"passed_time":2.897066377,"remaining_time":4.100678495},
{"learn":[0.3877732493],"iteration":414,"passed_time":2.902009111,"remaining_time":4.090783928},
{"learn":[0.3877135366],"iteration":415,"passed_time":2.906805641,"remaining_time":4.080707918},
{"learn":[0.3876934255],"iteration":416,"passed_time":2.911581087,"remaining_time":4.070627755},
{"learn":[0.3876142069],"iteration":417,"passed_time":2.916561196,"remaining_time":4.060857933},
{"learn":[0.3874912313],"iteration":418,"passed_time":2.921221478,"remaining_time":4.050667491},
{"learn":[0.3874266103],"iteration":419,"passed_time":2.926266752,"remaining_time":4.041035039},
{"learn":[0.3873067067],"iteration":420,"passed_time":2.931193529,"remaining_time":4.031261409},
{"learn":[0.3872581329],"iteration":421,"passed_time":2.93590006,"remaining_time":4.021209087},
{"learn":[0.3871686401],"iteration":422,"passed_time":2.941274786,"remaining_time":4.012093502},
{"learn":[0.3870307465],"iteration":423,"passed_time":2.946447724,"remaining_time":4.002721437},
{"learn":[0.3869102325],"iteration":424,"passed_time":2.951283837,"remaining_time":3.992913426},
{"learn":[0.3868006948],"iteration":425,"passed_time":2.95611399,"remaining_time":3.983120729},
{"learn":[0.3867418569],"iteration":426,"passed_time":2.960852646,"remaining_time":3.973228492},
{"learn":[0.3865789032],"iteration":427,"passed_time":2.965428597,"remaining_time":3.963142891},
{"learn":[0.3864984182],"iteration":428,"passed_time":2.975726474,"remaining_time":3.960698873},
{"learn":[0.3863623708],"iteration":429,"passed_time":2.986711005,"remaining_time":3.959128541},
{"learn":[0.3863038534],"iteration":430,"passed_time":2.992024483,"remaining_time":3.950027681},
{"learn":[0.3862530263],"iteration":431,"passed_time":2.996545725,"remaining_time":3.939902713},
{"learn":[0.3861684214],"iteration":432,"passed_time":3.00223257,"remaining_time":3.931329947},
{"learn":[0.3860735168],"iteration":433,"passed_time":3.006600608,"remaining_time":3.921050562},
{"learn":[0.3859616445],"iteration":434,"passed_time":3.011789046,"remaining_time":3.911863934},
{"learn":[0.3858247579],"iteration":435,"passed_time":3.017284978,"remaining_time":3.903093411},
{"learn":[0.3857478536],"iteration":436,"passed_time":3.02215638,"remaining_time":3.893533277},
{"learn":[0.3856375529],"iteration":437,"passed_time":3.027017116,"remaining_time":3.883980866},
{"learn":[0.3855485382],"iteration":438,"passed_time":3.032462133,"remaining_time":3.875196484},
{"learn":[0.3854208527],"iteration":439,"passed_time":3.03987386,"remaining_time":3.868930367},
{"learn":[0.3853304342],"iteration":440,"passed_time":3.060946731,"remaining_time":3.879975562},
{"learn":[0.3852198385],"iteration":441,"passed_time":3.073156612,"remaining_time":3.879686402},
{"learn":[0.385112676],"iteration":442,"passed_time":3.084212851,"remaining_time":3.877892907},
{"learn":[0.3849951528],"iteration":443,"passed_time":3.095845077,"remaining_time":3.87677897},
{"learn":[0.384908666],"iteration":444,"passed_time":3.104591194,"remaining_time":3.872018231},
{"learn":[0.3847617849],"iteration":445,"passed_time":3.113411393,"remaining_time":3.867331641},
{"learn":[0.3846790619],"iteration":446,"passed_time":3.120883036,"remaining_time":3.860958208},
{"learn":[0.3846048635],"iteration":447,"passed_time":3.126012059,"remaining_time":3.851693429},
{"learn":[0.3844846141],"iteration":448,"passed_time":3.130455095,"remaining_time":3.84160525},
{"learn":[0.3843620351],"iteration":449,"passed_time":3.135336081,"remaining_time":3.832077433},
{"learn":[0.3842170054],"iteration":450,"passed_time":3.140866763,"remaining_time":3.823361093},
{"learn":[0.3841127879],"iteration":451,"passed_time":3.146071159,"remaining_time":3.814263264},
{"learn":[0.3840168915],"iteration":452,"passed_time":3.151218848,"remaining_time":3.80511415},
{"learn":[0.3839515991],"iteration":453,"passed_time":3.155857673,"remaining_time":3.795370681},
{"learn":[0.3838539734],"iteration":454,"passed_time":3.161363022,"remaining_time":3.786687576},
{"learn":[0.3837574615],"iteration":455,"passed_time":3.166447587,"remaining_time":3.77751642},
{"learn":[0.3836678314],"iteration":456,"passed_time":3.171783481,"remaining_time":3.768661773},
{"learn":[0.3835868683],"iteration":457,"passed_time":3.178542763,"remaining_time":3.761506938},
{"learn":[0.3835037893],"iteration":458,"passed_time":3.184251399,"remaining_time":3.753115484},
{"learn":[0.383431015],"iteration":459,"passed_time":3.192218156,"remaining_time":3.747386531},
{"learn":[0.383373998],"iteration":460,"passed_time":3.202524491,"remaining_time":3.744383299},
{"learn":[0.3833262177],"iteration":461,"passed_time":3.210659329,"remaining_time":3.738819738},
{"learn":[0.3832240448],"iteration":462,"passed_time":3.223052374,"remaining_time":3.738183855},
{"learn":[0.3831569468],"iteration":463,"passed_time":3.228829841,"remaining_time":3.729855162},
{"learn":[0.3830341848],"iteration":464,"passed_time":3.235643497,"remaining_time":3.722729615},
{"learn":[0.3829673309],"iteration":465,"passed_time":3.242409904,"remaining_time":3.715551264},
{"learn":[0.3828593496],"iteration":466,"passed_time":3.250466869,"remaining_time":3.709847625},
{"learn":[0.3827860006],"iteration":467,"passed_time":3.256607454,"remaining_time":3.701955482},
{"learn":[0.382715627],"iteration":468,"passed_time":3.261923056,"remaining_time":3.693136765},
{"learn":[0.3825857137],"iteration":469,"passed_time":3.266921872,"remaining_time":3.683975728},
{"learn":[0.3824692891],"iteration":470,"passed_time":3.272119018,"remaining_time":3.675055118},
{"learn":[0.3823844706],"iteration":471,"passed_time":3.277282457,"remaining_time":3.666112579},
{"learn":[0.382256546],"iteration":472,"passed_time":3.282307398,"remaining_time":3.65703171},
{"learn":[0.3821331991],"iteration":473,"passed_time":3.287946536,"remaining_time":3.648649531},
{"learn":[0.3820629171],"iteration":474,"passed_time":3.293474717,"remaining_time":3.640156266},
{"learn":[0.3819742635],"iteration":475,"passed_time":3.29804496,"remaining_time":3.630620922},
{"learn":[0.381868988],"iteration":476,"passed_time":3.303173941,"remaining_time":3.621719017},
{"learn":[0.3817674408],"iteration":477,"passed_time":3.30780264,"remaining_time":3.612286565},
{"learn":[0.3816593374],"iteration":478,"passed_time":3.312923121,"remaining_time":3.603409073},
{"learn":[0.3815909729],"iteration":479,"passed_time":3.317423822,"remaining_time":3.593875807},
{"learn":[0.3815258942],"iteration":480,"passed_time":3.322925212,"remaining_time":3.585443213},
{"learn":[0.3813975372],"iteration":481,"passed_time":3.331037384,"remaining_time":3.579828557},
{"learn":[0.3813152161],"iteration":482,"passed_time":3.337932663,"remaining_time":3.572901008},
{"learn":[0.3811837667],"iteration":483,"passed_time":3.344414659,"remaining_time":3.565532983},
{"learn":[0.3811101125],"iteration":484,"passed_time":3.351908884,"remaining_time":3.559243454},
{"learn":[0.3810267385],"iteration":485,"passed_time":3.362438049,"remaining_time":3.556158759},
{"learn":[0.3809443003],"iteration":486,"passed_time":3.36899346,"remaining_time":3.548857587},
{"learn":[0.3808389333],"iteration":487,"passed_time":3.375320751,"remaining_time":3.541320132},
{"learn":[0.3807892456],"iteration":488,"passed_time":3.381219549,"remaining_time":3.533339856},
{"learn":[0.3807197011],"iteration":489,"passed_time":3.387141931,"remaining_time":3.525392622},
{"learn":[0.3805957743],"iteration":490,"passed_time":3.394176248,"remaining_time":3.518606335},
{"learn":[0.3804869232],"iteration":491,"passed_time":3.401836761,"remaining_time":3.512465599},
{"learn":[0.3804216665],"iteration":492,"passed_time":3.407080074,"remaining_time":3.503832855},
{"learn":[0.3803026784],"iteration":493,"passed_time":3.412684212,"remaining_time":3.495583424},
{"learn":[0.3802289276],"iteration":494,"passed_time":3.420881131,"remaining_time":3.489989841},
{"learn":[0.3801312764],"iteration":495,"passed_time":3.427279546,"remaining_time":3.482558248},
{"learn":[0.3800545553],"iteration":496,"passed_time":3.436742899,"remaining_time":3.478232753},
{"learn":[0.3799486847],"iteration":497,"passed_time":3.441942129,"remaining_time":3.469588251},
{"learn":[0.3798478495],"iteration":498,"passed_time":3.451182153,"remaining_time":3.465014546},
{"learn":[0.3797604624],"iteration":499,"passed_time":3.455933724,"remaining_time":3.455933724},
{"learn":[0.3796951497],"iteration":500,"passed_time":3.460047434,"remaining_time":3.446234869},
{"learn":[0.3795723979],"iteration":501,"passed_time":3.46908942,"remaining_time":3.441447273},
{"learn":[0.3794847768],"iteration":502,"passed_time":3.479818039,"remaining_time":3.438309275},
{"learn":[0.3793786926],"iteration":503,"passed_time":3.493449476,"remaining_time":3.437997897},
{"learn":[0.3793094126],"iteration":504,"passed_time":3.50927691,"remaining_time":3.439786278},
{"learn":[0.3791939138],"iteration":505,"passed_time":3.52335417,"remaining_time":3.439796364},
{"learn":[0.3791383311],"iteration":506,"passed_time":3.531824334,"remaining_time":3.434298613},
{"learn":[0.379046814],"iteration":507,"passed_time":3.543956509,"remaining_time":3.432335832},
{"learn":[0.3789743296],"iteration":508,"passed_time":3.555454572,"remaining_time":3.429721404},
{"learn":[0.3788703613],"iteration":509,"passed_time":3.56763712,"remaining_time":3.427729782},
{"learn":[0.3787905375],"iteration":510,"passed_time":3.578225576,"remaining_time":3.424172812},
{"learn":[0.3787097066],"iteration":511,"passed_time":3.594948742,"remaining_time":3.42643552},
{"learn":[0.3785827281],"iteration":512,"passed_time":3.608851507,"remaining_time":3.425946752},
{"learn":[0.3784919179],"iteration":513,"passed_time":3.623467257,"remaining_time":3.426079936},
{"learn":[0.3784069875],"iteration":514,"passed_time":3.636569537,"remaining_time":3.424730534},
{"learn":[0.3783423767],"iteration":515,"passed_time":3.648317135,"remaining_time":3.42206491},
{"learn":[0.378259201],"iteration":516,"passed_time":3.669978203,"remaining_time":3.428625671},
{"learn":[0.3781439565],"iteration":517,"passed_time":3.68757631,"remaining_time":3.431296875},
{"learn":[0.3780723012],"iteration":518,"passed_time":3.694975912,"remaining_time":3.424438177},
{"learn":[0.3780124308],"iteration":519,"passed_time":3.70551091,"remaining_time":3.420471609},
{"learn":[0.3779211477],"iteration":520,"passed_time":3.718880018,"remaining_time":3.419085467},
{"learn":[0.3778628133],"iteration":521,"passed_time":3.724449199,"remaining_time":3.410510952},
{"learn":[0.3778267822],"iteration":522,"passed_time":3.730602493,"remaining_time":3.402480667},
{"learn":[0.3777783915],"iteration":523,"passed_time":3.741115742,"remaining_time":3.398418117},
{"learn":[0.3776871389],"iteration":524,"passed_time":3.747070081,"remaining_time":3.390206264},
{"learn":[0.3776257324],"iteration":525,"passed_time":3.752446808,"remaining_time":3.381482485},
{"learn":[0.377581309],"iteration":526,"passed_time":3.761317673,"remaining_time":3.375907513},
{"learn":[0.3775161184],"iteration":527,"passed_time":3.76646807,"remaining_time":3.366994184},
{"learn":[0.3774731852],"iteration":528,"passed_time":3.773444348,"remaining_time":3.359720771},
{"learn":[0.3773560994],"iteration":529,"passed_time":3.778123671,"remaining_time":3.350411558},
{"learn":[0.3772824504],"iteration":530,"passed_time":3.782004886,"remaining_time":3.340414862},
{"learn":[0.377206487],"iteration":531,"passed_time":3.78555619,"remaining_time":3.330150934},
{"learn":[0.3771256256],"iteration":532,"passed_time":3.790609797,"remaining_time":3.321228471},
{"learn":[0.3770268351],"iteration":533,"passed_time":3.795287579,"remaining_time":3.311992531},
{"learn":[0.3769418233],"iteration":534,"passed_time":3.800284146,"remaining_time":3.303050706},
{"learn":[0.3768731181],"iteration":535,"passed_time":3.806607478,"remaining_time":3.295272145},
{"learn":[0.3767466634],"iteration":536,"passed_time":3.814712941,"remaining_time":3.289035553},
{"learn":[0.3766529083],"iteration":537,"passed_time":3.821152772,"remaining_time":3.281361674},
{"learn":[0.3765390371],"iteration":538,"passed_time":3.827273149,"remaining_time":3.27341915},
{"learn":[0.3764465027],"iteration":539,"passed_time":3.832357298,"remaining_time":3.264600661},
{"learn":[0.3763972626],"iteration":540,"passed_time":3.837852979,"remaining_time":3.256145134},
{"learn":[0.3763128866],"iteration":541,"passed_time":3.843106582,"remaining_time":3.247495968},
{"learn":[0.3762529246],"iteration":542,"passed_time":3.847790656,"remaining_time":3.238379981},
{"learn":[0.3761358541],"iteration":543,"passed_time":3.852926511,"remaining_time":3.229658988},
{"learn":[0.3761003571],"iteration":544,"passed_time":3.857423714,"remaining_time":3.220417963},
{"learn":[0.3760432739],"iteration":545,"passed_time":3.863516342,"remaining_time":3.212520914},
{"learn":[0.3759967499],"iteration":546,"passed_time":3.88069729,"remaining_time":3.213813295},
{"learn":[0.3759009857],"iteration":547,"passed_time":3.895633158,"remaining_time":3.213186473},
{"learn":[0.375864507],"iteration":548,"passed_time":3.906218072,"remaining_time":3.208933243},
{"learn":[0.3757725779],"iteration":549,"passed_time":3.918032794,"remaining_time":3.205663195},
{"learn":[0.3756766154],"iteration":550,"passed_time":3.929790059,"remaining_time":3.202315312},
{"learn":[0.3755492961],"iteration":551,"passed_time":3.940530804,"remaining_time":3.198111957},
{"learn":[0.3754947662],"iteration":552,"passed_time":3.950883597,"remaining_time":3.193571371},
{"learn":[0.3754587301],"iteration":553,"passed_time":3.961205683,"remaining_time":3.188985081},
{"learn":[0.3753637797],"iteration":554,"passed_time":3.971147485,"remaining_time":3.184073209},
{"learn":[0.3752987213],"iteration":555,"passed_time":3.982591382,"remaining_time":3.180342758},
{"learn":[0.3752095998],"iteration":556,"passed_time":3.990923882,"remaining_time":3.174110018},
{"learn":[0.3751678365],"iteration":557,"passed_time":4.000078824,"remaining_time":3.168521219},
{"learn":[0.375072403],"iteration":558,"passed_time":4.007762546,"remaining_time":3.161759003},
{"learn":[0.3750133464],"iteration":559,"passed_time":4.017541517,"remaining_time":3.156639763},
{"learn":[0.3749085083],"iteration":560,"passed_time":4.023756976,"remaining_time":3.148715352},
{"learn":[0.3748227183],"iteration":561,"passed_time":4.028979247,"remaining_time":3.140022972},
{"learn":[0.3747493083],"iteration":562,"passed_time":4.034067687,"remaining_time":3.13123904},
{"learn":[0.3746414388],"iteration":563,"passed_time":4.038841384,"remaining_time":3.1222249},
{"learn":[0.3745555725],"iteration":564,"passed_time":4.043375918,"remaining_time":3.113041636},
{"learn":[0.3744967194],"iteration":565,"passed_time":4.048307028,"remaining_time":3.104178887},
{"learn":[0.374374471],"iteration":566,"passed_time":4.053368885,"remaining_time":3.095429854},
{"learn":[0.3742774455],"iteration":567,"passed_time":4.058794736,"remaining_time":3.086970644},
{"learn":[0.3742485911],"iteration":568,"passed_time":4.063525141,"remaining_time":3.077995318},
{"learn":[0.3741882273],"iteration":569,"passed_time":4.068936324,"remaining_time":3.069548455},
{"learn":[0.374125234],"iteration":570,"passed_time":4.074130554,"remaining_time":3.060949225},
{"learn":[0.3739973907],"iteration":571,"passed_time":4.079395407,"remaining_time":3.052414745},
{"learn":[0.3739602559],"iteration":572,"passed_time":4.084376683,"remaining_time":3.043680355},
{"learn":[0.3738710734],"iteration":573,"passed_time":4.090230483,"remaining_time":3.035606596},
{"learn":[0.3737763112],"iteration":574,"passed_time":4.095540086,"remaining_time":3.027138325},
{"learn":[0.3737175344],"iteration":575,"passed_time":4.100715942,"remaining_time":3.018582568},
{"learn":[0.373639033],"iteration":576,"passed_time":4.105307558,"remaining_time":3.00961022},
{"learn":[0.3735676219],"iteration":577,"passed_time":4.110167544,"remaining_time":3.000848968},
{"learn":[0.3734682465],"iteration":578,"passed_time":4.114620705,"remaining_time":2.991805383},
{"learn":[0.3733911591],"iteration":579,"passed_time":4.120441672,"remaining_time":2.983768107},
{"learn":[0.3733263957],"iteration":580,"passed_time":4.126838087,"remaining_time":2.976153457},
{"learn":[0.3732560374],"iteration":581,"passed_time":4.132251687,"remaining_time":2.967837122},
{"learn":[0.3731897532],"iteration":582,"passed_time":4.142372652,"remaining_time":2.962897763},
{"learn":[0.373148524],"iteration":583,"passed_time":4.151170392,"remaining_time":2.956998087},
{"learn":[0.3730258738],"iteration":584,"passed_time":4.159644765,"remaining_time":2.950859107},
{"learn":[0.3729414571],"iteration":585,"passed_time":4.164796704,"remaining_time":2.942364907},
{"learn":[0.372857137],"iteration":586,"passed_time":4.178050231,"remaining_time":2.93958219},
{"learn":[0.3727680054],"iteration":587,"passed_time":4.190962682,"remaining_time":2.936524872},
{"learn":[0.3727106832],"iteration":588,"passed_time":4.203475974,"remaining_time":2.933155561},
{"learn":[0.3726512502],"iteration":589,"passed_time":4.211895347,"remaining_time":2.926910326},
{"learn":[0.3725740611],"iteration":590,"passed_time":4.218513049,"remaining_time":2.919410892},
{"learn":[0.372475235],"iteration":591,"passed_time":4.225614282,"remaining_time":2.912247681},
{"learn":[0.3723727519],"iteration":592,"passed_time":4.230257064,"remaining_time":2.903397344},
{"learn":[0.372274353],"iteration":593,"passed_time":4.235081384,"remaining_time":2.894685256},
{"learn":[0.3722083079],"iteration":594,"passed_time":4.240066202,"remaining_time":2.886095482},
{"learn":[0.3721603495],"iteration":595,"passed_time":4.24578867,"remaining_time":2.878017824},
{"learn":[0.3720749766],"iteration":596,"passed_time":4.251167521,"remaining_time":2.869716099},
{"learn":[0.3720141195],"iteration":597,"passed_time":4.256655995,"remaining_time":2.861497843},
{"learn":[0.3719285431],"iteration":598,"passed_time":4.261472064,"remaining_time":2.852838561},
{"learn":[0.3718684133],"iteration":599,"passed_time":4.266370759,"remaining_time":2.844247172},
{"learn":[0.3718171743],"iteration":600,"passed_time":4.275003544,"remaining_time":2.838147112},
{"learn":[0.3717440999],"iteration":601,"passed_time":4.280804012,"remaining_time":2.830166107},
{"learn":[0.3716297658],"iteration":602,"passed_time":4.288873851,"remaining_time":2.823686432},
{"learn":[0.3715507914],"iteration":603,"passed_time":4.295287223,"remaining_time":2.816115464},
{"learn":[0.3714843699],"iteration":604,"passed_time":4.300718614,"remaining_time":2.807907194},
{"learn":[0.3714258779],"iteration":605,"passed_time":4.30651454,"remaining_time":2.799945097},
{"learn":[0.3713295186],"iteration":606,"passed_time":4.31284758,"remaining_time":2.79233789},
{"learn":[0.3712633921],"iteration":607,"passed_time":4.321396618,"remaining_time":2.786163609},
{"learn":[0.3711825816],"iteration":608,"passed_time":4.326282188,"remaining_time":2.777629451},
{"learn":[0.3711097463],"iteration":609,"passed_time":4.330744682,"remaining_time":2.768836764},
{"learn":[0.371039271],"iteration":610,"passed_time":4.335253467,"remaining_time":2.760087723},
{"learn":[0.3709749603],"iteration":611,"passed_time":4.340055829,"remaining_time":2.751538663},
{"learn":[0.3709462026],"iteration":612,"passed_time":4.344956231,"remaining_time":2.743063722},
{"learn":[0.3709182485],"iteration":613,"passed_time":4.350003923,"remaining_time":2.73469302},
{"learn":[0.3708532715],"iteration":614,"passed_time":4.354856701,"remaining_time":2.726211105},
{"learn":[0.3707839559],"iteration":615,"passed_time":4.359805685,"remaining_time":2.717800946},
{"learn":[0.3706995494],"iteration":616,"passed_time":4.367586447,"remaining_time":2.71115982},
{"learn":[0.370576884],"iteration":617,"passed_time":4.374816843,"remaining_time":2.704174813},
{"learn":[0.3705083923],"iteration":618,"passed_time":4.380289984,"remaining_time":2.696107405},
{"learn":[0.3704513041],"iteration":619,"passed_time":4.385593295,"remaining_time":2.687944278},
{"learn":[0.3703586528],"iteration":620,"passed_time":4.392193204,"remaining_time":2.680581682},
{"learn":[0.3702974904],"iteration":621,"passed_time":4.406593417,"remaining_time":2.677961916},
{"learn":[0.3702062785],"iteration":622,"passed_time":4.416878545,"remaining_time":2.672814143},
{"learn":[0.3701451518],"iteration":623,"passed_time":4.426634141,"remaining_time":2.667330829},
{"learn":[0.3700105337],"iteration":624,"passed_time":4.436244491,"remaining_time":2.661746695},
{"learn":[0.3699455617],"iteration":625,"passed_time":4.448049381,"remaining_time":2.657460812},
{"learn":[0.369841629],"iteration":626,"passed_time":4.457211823,"remaining_time":2.651578963},
{"learn":[0.369702891],"iteration":627,"passed_time":4.465178664,"remaining_time":2.644978444},
{"learn":[0.3696053009],"iteration":628,"passed_time":4.471436581,"remaining_time":2.637365614},
{"learn":[0.3695099792],"iteration":629,"passed_time":4.477206799,"remaining_time":2.62947066},
{"learn":[0.3694338328],"iteration":630,"passed_time":4.484302782,"remaining_time":2.622357728},
{"learn":[0.3693672841],"iteration":631,"passed_time":4.489815797,"remaining_time":2.614323122},
{"learn":[0.3692940369],"iteration":632,"passed_time":4.498019049,"remaining_time":2.607856226},
{"learn":[0.3691993357],"iteration":633,"passed_time":4.510677589,"remaining_time":2.603955832},
{"learn":[0.3691412303],"iteration":634,"passed_time":4.518845509,"remaining_time":2.597446631},
{"learn":[0.369085556],"iteration":635,"passed_time":4.524702559,"remaining_time":2.589609641},
{"learn":[0.3689856618],"iteration":636,"passed_time":4.532422238,"remaining_time":2.582840302},
{"learn":[0.3689123637],"iteration":637,"passed_time":4.537383764,"remaining_time":2.574503013},
{"learn":[0.3688469391],"iteration":638,"passed_time":4.543041484,"remaining_time":2.566569602},
{"learn":[0.3687519989],"iteration":639,"passed_time":4.548094091,"remaining_time":2.558302926},
{"learn":[0.368671758],"iteration":640,"passed_time":4.555290822,"remaining_time":2.551247122},
{"learn":[0.3685827281],"iteration":641,"passed_time":4.560211265,"remaining_time":2.542921547},
{"learn":[0.3684975332],"iteration":642,"passed_time":4.564930337,"remaining_time":2.534494759},
{"learn":[0.3684614563],"iteration":643,"passed_time":4.569423414,"remaining_time":2.525954558},
{"learn":[0.3683553772],"iteration":644,"passed_time":4.573956908,"remaining_time":2.517449151},
{"learn":[0.3682744293],"iteration":645,"passed_time":4.579114264,"remaining_time":2.509297909},
{"learn":[0.3681748708],"iteration":646,"passed_time":4.584494698,"remaining_time":2.501277633},
{"learn":[0.3680717672],"iteration":647,"passed_time":4.589800634,"remaining_time":2.493225035},
{"learn":[0.3679999593],"iteration":648,"passed_time":4.594832075,"remaining_time":2.485032447},
{"learn":[0.3679208069],"iteration":649,"passed_time":4.600787622,"remaining_time":2.477347181},
{"learn":[0.3678783569],"iteration":650,"passed_time":4.605869813,"remaining_time":2.469199024},
{"learn":[0.3678009796],"iteration":651,"passed_time":4.610922587,"remaining_time":2.461044571},
{"learn":[0.3677179159],"iteration":652,"passed_time":4.615546454,"remaining_time":2.452671699},
{"learn":[0.3676151072],"iteration":653,"passed_time":4.620825932,"remaining_time":2.444657145},
{"learn":[0.3675329946],"iteration":654,"passed_time":4.625583587,"remaining_time":2.436376088},
{"learn":[0.3674637705],"iteration":655,"passed_time":4.630498697,"remaining_time":2.428188341},
{"learn":[0.3673707581],"iteration":656,"passed_time":4.636662782,"remaining_time":2.420662609},
{"learn":[0.3673089956],"iteration":657,"passed_time":4.642050466,"remaining_time":2.412737476},
{"learn":[0.367244868],"iteration":658,"passed_time":4.647237653,"remaining_time":2.404716297},
{"learn":[0.3671661886],"iteration":659,"passed_time":4.652764668,"remaining_time":2.396878768},
{"learn":[0.3670724894],"iteration":660,"passed_time":4.657687153,"remaining_time":2.388738192},
{"learn":[0.3669492798],"iteration":661,"passed_time":4.662547598,"remaining_time":2.380575662},
{"learn":[0.3668804779],"iteration":662,"passed_time":4.667090424,"remaining_time":2.372261648},
{"learn":[0.3668255819],"iteration":663,"passed_time":4.671883244,"remaining_time":2.364085497},
{"learn":[0.3667629598],"iteration":664,"passed_time":4.676664982,"remaining_time":2.355913938},
{"learn":[0.3666771851],"iteration":665,"passed_time":4.681840545,"remaining_time":2.347950063},
{"learn":[0.3666107941],"iteration":666,"passed_time":4.686670031,"remaining_time":2.33982177},
{"learn":[0.3665431468],"iteration":667,"passed_time":4.695611978,"remaining_time":2.33374727},
{"learn":[0.3664532471],"iteration":668,"passed_time":4.706793588,"remaining_time":2.328772313},
{"learn":[0.366368454],"iteration":669,"passed_time":4.718824764,"remaining_time":2.324197272},
{"learn":[0.3662721965],"iteration":670,"passed_time":4.728828649,"remaining_time":2.318605999},
{"learn":[0.3662099762],"iteration":671,"passed_time":4.733763633,"remaining_time":2.310527488},
{"learn":[0.3661268717],"iteration":672,"passed_time":4.740708412,"remaining_time":2.303434845},
{"learn":[0.366052887],"iteration":673,"passed_time":4.74805464,"remaining_time":2.296536814},
{"learn":[0.3659925537],"iteration":674,"passed_time":4.755149498,"remaining_time":2.289516425},
{"learn":[0.3659213053],"iteration":675,"passed_time":4.761581537,"remaining_time":2.282178133},
{"learn":[0.3658320719],"iteration":676,"passed_time":4.767204508,"remaining_time":2.274456508},
{"learn":[0.3657545827],"iteration":677,"passed_time":4.774141077,"remaining_time":2.267364936},
{"learn":[0.3656823934],"iteration":678,"passed_time":4.780240998,"remaining_time":2.259878292},
{"learn":[0.3656138306],"iteration":679,"passed_time":4.784997112,"remaining_time":2.251763347},
{"learn":[0.3655263418],"iteration":680,"passed_time":4.792475962,"remaining_time":2.244933674},
{"learn":[0.3654770966],"iteration":681,"passed_time":4.797543028,"remaining_time":2.236977541},
{"learn":[0.3654220225],"iteration":682,"passed_time":4.802523096,"remaining_time":2.22898949},
{"learn":[0.3653213755],"iteration":683,"passed_time":4.807728159,"remaining_time":2.221114179},
{"learn":[0.3652481028],"iteration":684,"passed_time":4.814751186,"remaining_time":2.214082662},
{"learn":[0.3651871948],"iteration":685,"passed_time":4.819994373,"remaining_time":2.206236492},
{"learn":[0.3650765788],"iteration":686,"passed_time":4.825696592,"remaining_time":2.198607036},
{"learn":[0.365031723],"iteration":687,"passed_time":4.83126094,"remaining_time":2.190920659},
{"learn":[0.3649620972],"iteration":688,"passed_time":4.836418462,"remaining_time":2.18305681},
{"learn":[0.3649105886],"iteration":689,"passed_time":4.842880667,"remaining_time":2.175786967},
{"learn":[0.3648441518],"iteration":690,"passed_time":4.84773982,"remaining_time":2.167802611},
{"learn":[0.364767924],"iteration":691,"passed_time":4.852450351,"remaining_time":2.159761139},
{"learn":[0.3647072245],"iteration":692,"passed_time":4.858605687,"remaining_time":2.15236933},
{"learn":[0.3646089528],"iteration":693,"passed_time":4.86411816,"remaining_time":2.144697632},
{"learn":[0.3645530039],"iteration":694,"passed_time":4.870169456,"remaining_time":2.13726861},
{"learn":[0.3644954122],"iteration":695,"passed_time":4.875414226,"remaining_time":2.129491271},
{"learn":[0.3644445852],"iteration":696,"passed_time":4.882993783,"remaining_time":2.122736178},
{"learn":[0.3644015045],"iteration":697,"passed_time":4.888834374,"remaining_time":2.115226334},
{"learn":[0.3643271484],"iteration":698,"passed_time":4.893969856,"remaining_time":2.107417635},
{"learn":[0.3642781067],"iteration":699,"passed_time":4.899728825,"remaining_time":2.099883782},
{"learn":[0.3642303823],"iteration":700,"passed_time":4.904866514,"remaining_time":2.092089997},
{"learn":[0.3641384633],"iteration":701,"passed_time":4.910131909,"remaining_time":2.08435799},
{"learn":[0.3640612488],"iteration":702,"passed_time":4.917268559,"remaining_time":2.077423559},
{"learn":[0.3640182699],"iteration":703,"passed_time":4.922133504,"remaining_time":2.069533405},
{"learn":[0.3639482981],"iteration":704,"passed_time":4.927321608,"remaining_time":2.061787056},
{"learn":[0.3639223582],"iteration":705,"passed_time":4.931987848,"remaining_time":2.053830634},
{"learn":[0.3638535207],"iteration":706,"passed_time":4.936881083,"remaining_time":2.045977592},
{"learn":[0.3637881673],"iteration":707,"passed_time":4.94193544,"remaining_time":2.038199362},
{"learn":[0.3637133942],"iteration":708,"passed_time":4.947355499,"remaining_time":2.030578914},
{"learn":[0.3636166331],"iteration":709,"passed_time":4.951766286,"remaining_time":2.022552427},
{"learn":[0.3635639699],"iteration":710,"passed_time":4.956778561,"remaining_time":2.014780597},
{"learn":[0.3634719086],"iteration":711,"passed_time":4.963939293,"remaining_time":2.007885557},
{"learn":[0.3634251302],"iteration":712,"passed_time":4.971530975,"remaining_time":2.001163239},
{"learn":[0.3633531952],"iteration":713,"passed_time":4.990090562,"remaining_time":1.998831794},
{"learn":[0.3632997538],"iteration":714,"passed_time":5.006836936,"remaining_time":1.995732205},
{"learn":[0.3631997172],"iteration":715,"passed_time":5.01541939,"remaining_time":1.989356294},
{"learn":[0.3631192017],"iteration":716,"passed_time":5.021176067,"remaining_time":1.981858894},
{"learn":[0.363012736],"iteration":717,"passed_time":5.026674873,"remaining_time":1.974265062},
{"learn":[0.3629233653],"iteration":718,"passed_time":5.033060496,"remaining_time":1.967023643},
{"learn":[0.3628450368],"iteration":719,"passed_time":5.037928607,"remaining_time":1.959194458},
{"learn":[0.362746521],"iteration":720,"passed_time":5.043466621,"remaining_time":1.951632715},
{"learn":[0.3626888529],"iteration":721,"passed_time":5.050728726,"remaining_time":1.944740424},
{"learn":[0.3626059316],"iteration":722,"passed_time":5.055517339,"remaining_time":1.936899451},
{"learn":[0.3625411936],"iteration":723,"passed_time":5.061484469,"remaining_time":1.929516179},
{"learn":[0.3624699402],"iteration":724,"passed_time":5.068516454,"remaining_time":1.922540724},
{"learn":[0.362367569],"iteration":725,"passed_time":5.07366906,"remaining_time":1.914855816},
{"learn":[0.3622710012],"iteration":726,"passed_time":5.080150014,"remaining_time":1.90767669},
{"learn":[0.3622262421],"iteration":727,"passed_time":5.085149122,"remaining_time":1.899945826},
{"learn":[0.3621241252],"iteration":728,"passed_time":5.090590931,"remaining_time":1.892387026},
{"learn":[0.3620237223],"iteration":729,"passed_time":5.096598186,"remaining_time":1.885043165},
{"learn":[0.3619766541],"iteration":730,"passed_time":5.103230011,"remaining_time":1.877932795},
{"learn":[0.3619246979],"iteration":731,"passed_time":5.108428075,"remaining_time":1.870298803},
{"learn":[0.3618749186],"iteration":732,"passed_time":5.116634828,"remaining_time":1.863767393},
{"learn":[0.3617502594],"iteration":733,"passed_time":5.122082552,"remaining_time":1.856231552},
{"learn":[0.3617160899],"iteration":734,"passed_time":5.128757961,"remaining_time":1.849144027},
{"learn":[0.3616540782],"iteration":735,"passed_time":5.135655823,"remaining_time":1.842137415},
{"learn":[0.361543045],"iteration":736,"passed_time":5.140777012,"remaining_time":1.834497088},
{"learn":[0.361500885],"iteration":737,"passed_time":5.14837486,"remaining_time":1.827742837},
{"learn":[0.3614051768],"iteration":738,"passed_time":5.154962937,"remaining_time":1.82062967},
{"learn":[0.3613431193],"iteration":739,"passed_time":5.163696178,"remaining_time":1.81427163},
{"learn":[0.3612755992],"iteration":740,"passed_time":5.168743453,"remaining_time":1.806618832},
{"learn":[0.3612219187],"iteration":741,"passed_time":5.174515422,"remaining_time":1.799225039},
{"learn":[0.3611337636],"iteration":742,"passed_time":5.181940648,"remaining_time":1.792407465},
{"learn":[0.3610748749],"iteration":743,"passed_time":5.186981756,"remaining_time":1.784767916},
{"learn":[0.3609854329],"iteration":744,"passed_time":5.192695809,"remaining_time":1.777365679},
{"learn":[0.3608968709],"iteration":745,"passed_time":5.199166846,"remaining_time":1.770225709},
{"learn":[0.3608246155],"iteration":746,"passed_time":5.204241453,"remaining_time":1.762614575},
{"learn":[0.3607616628],"iteration":747,"passed_time":5.21032929,"remaining_time":1.755351579},
{"learn":[0.3606585693],"iteration":748,"passed_time":5.215421063,"remaining_time":1.747757926},
{"learn":[0.360600886],"iteration":749,"passed_time":5.220315049,"remaining_time":1.740105016},
{"learn":[0.3605793355],"iteration":750,"passed_time":5.226086059,"remaining_time":1.732750238},
{"learn":[0.3605250397],"iteration":751,"passed_time":5.231421286,"remaining_time":1.725255956},
{"learn":[0.36045342],"iteration":752,"passed_time":5.237325835,"remaining_time":1.717954158},
{"learn":[0.3603986206],"iteration":753,"passed_time":5.242745477,"remaining_time":1.710497861},
{"learn":[0.3603382009],"iteration":754,"passed_time":5.247867833,"remaining_time":1.702950489},
{"learn":[0.3602716471],"iteration":755,"passed_time":5.253185893,"remaining_time":1.695472696},
{"learn":[0.3601972758],"iteration":756,"passed_time":5.258416956,"remaining_time":1.687972682},
{"learn":[0.3601190491],"iteration":757,"passed_time":5.26346723,"remaining_time":1.680420936},
{"learn":[0.3600427958],"iteration":758,"passed_time":5.269708356,"remaining_time":1.673253905},
{"learn":[0.3600016683],"iteration":759,"passed_time":5.274648216,"remaining_time":1.665678384},
{"learn":[0.3599308726],"iteration":760,"passed_time":5.280012818,"remaining_time":1.658243185},
{"learn":[0.3598964081],"iteration":761,"passed_time":5.285343004,"remaining_time":1.65080267},
{"learn":[0.3598744151],"iteration":762,"passed_time":5.290930142,"remaining_time":1.643447502},
{"learn":[0.3597983958],"iteration":763,"passed_time":5.295847294,"remaining_time":1.635890002},
{"learn":[0.3597380422],"iteration":764,"passed_time":5.301304102,"remaining_time":1.628505182},
{"learn":[0.3596757355],"iteration":765,"passed_time":5.306337711,"remaining_time":1.620996115},
{"learn":[0.3596433512],"iteration":766,"passed_time":5.31077008,"remaining_time":1.613310859},
{"learn":[0.3595300039],"iteration":767,"passed_time":5.315588734,"remaining_time":1.605750763},
{"learn":[0.3594575246],"iteration":768,"passed_time":5.320586801,"remaining_time":1.598251692},
{"learn":[0.3594099426],"iteration":769,"passed_time":5.325702532,"remaining_time":1.590794263},
{"learn":[0.3593371938],"iteration":770,"passed_time":5.33056931,"remaining_time":1.583268965},
{"learn":[0.3592472076],"iteration":771,"passed_time":5.335661541,"remaining_time":1.575817139},
{"learn":[0.3591257985],"iteration":772,"passed_time":5.341470884,"remaining_time":1.568582006},
{"learn":[0.3590515137],"iteration":773,"passed_time":5.347103022,"remaining_time":1.561298815},
{"learn":[0.3589924723],"iteration":774,"passed_time":5.352449082,"remaining_time":1.55393683},
{"learn":[0.3589267832],"iteration":775,"passed_time":5.357444942,"remaining_time":1.546478952},
{"learn":[0.3588702342],"iteration":776,"passed_time":5.362336719,"remaining_time":1.53899754},
{"learn":[0.358823878],"iteration":777,"passed_time":5.367066458,"remaining_time":1.531476547},
{"learn":[0.3587922363],"iteration":778,"passed_time":5.371677199,"remaining_time":1.523928962},
{"learn":[0.3587288615],"iteration":779,"passed_time":5.376497394,"remaining_time":1.516447983},
{"learn":[0.3587019857],"iteration":780,"passed_time":5.381440088,"remaining_time":1.509008168},
{"learn":[0.3586261393],"iteration":781,"passed_time":5.386822605,"remaining_time":1.50169735},
{"learn":[0.3585468241],"iteration":782,"passed_time":5.391354223,"remaining_time":1.49415564},
{"learn":[0.3584659526],"iteration":783,"passed_time":5.396033337,"remaining_time":1.486662246},
{"learn":[0.3583813324],"iteration":784,"passed_time":5.400365793,"remaining_time":1.479081077},
{"learn":[0.3583270467],"iteration":785,"passed_time":5.404431628,"remaining_time":1.471435583},
{"learn":[0.3582510122],"iteration":786,"passed_time":5.409617858,"remaining_time":1.464102419},
{"learn":[0.3581749725],"iteration":787,"passed_time":5.414104228,"remaining_time":1.456586417},
{"learn":[0.3581348623],"iteration":788,"passed_time":5.418920882,"remaining_time":1.449166421},
{"learn":[0.3581033478],"iteration":789,"passed_time":5.42366812,"remaining_time":1.441734563},
{"learn":[0.3580243937],"iteration":790,"passed_time":5.429098969,"remaining_time":1.43449012},
{"learn":[0.3579933675],"iteration":791,"passed_time":5.434747857,"remaining_time":1.427307518},
{"learn":[0.3579795787],"iteration":792,"passed_time":5.440914317,"remaining_time":1.420263888},
{"learn":[0.3579418488],"iteration":793,"passed_time":5.447321855,"remaining_time":1.413285015},
{"learn":[0.3578951823],"iteration":794,"passed_time":5.455344903,"remaining_time":1.406724157},
{"learn":[0.3578512014],"iteration":795,"passed_time":5.46523583,"remaining_time":1.400638328},
{"learn":[0.3577966054],"iteration":796,"passed_time":5.47142929,"remaining_time":1.393601187},
{"learn":[0.3577499084],"iteration":797,"passed_time":5.477474002,"remaining_time":1.386528507},
{"learn":[0.3576803182],"iteration":798,"passed_time":5.483947373,"remaining_time":1.379566235},
{"learn":[0.3575914815],"iteration":799,"passed_time":5.495258688,"remaining_time":1.373814672},
{"learn":[0.357584142],"iteration":800,"passed_time":5.500035801,"remaining_time":1.366425873},
{"learn":[0.3574756877],"iteration":801,"passed_time":5.507023328,"remaining_time":1.3595893},
{"learn":[0.3573656413],"iteration":802,"passed_time":5.517882152,"remaining_time":1.353702097},
{"learn":[0.3572883759],"iteration":803,"passed_time":5.529731833,"remaining_time":1.348044079},
{"learn":[0.3571493429],"iteration":804,"passed_time":5.536120789,"remaining_time":1.341047893},
{"learn":[0.3570729065],"iteration":805,"passed_time":5.543985298,"remaining_time":1.334408372},
{"learn":[0.3569970398],"iteration":806,"passed_time":5.550068052,"remaining_time":1.327339695},
{"learn":[0.3569350993],"iteration":807,"passed_time":5.558545425,"remaining_time":1.320842477},
{"learn":[0.3568600413],"iteration":808,"passed_time":5.563428911,"remaining_time":1.313491869},
{"learn":[0.3568155721],"iteration":809,"passed_time":5.569815825,"remaining_time":1.306500008},
{"learn":[0.3567709808],"iteration":810,"passed_time":5.574272527,"remaining_time":1.299059812},
{"learn":[0.3567000326],"iteration":811,"passed_time":5.579244886,"remaining_time":1.291746353},
{"learn":[0.3566020101],"iteration":812,"passed_time":5.585374305,"remaining_time":1.284704791},
{"learn":[0.3565389048],"iteration":813,"passed_time":5.591431019,"remaining_time":1.277648857},
{"learn":[0.3564921672],"iteration":814,"passed_time":5.597021615,"remaining_time":1.270489569},
{"learn":[0.3564053141],"iteration":815,"passed_time":5.603353364,"remaining_time":1.263501249},
{"learn":[0.3562692617],"iteration":816,"passed_time":5.608529968,"remaining_time":1.256255795},
{"learn":[0.3562021484],"iteration":817,"passed_time":5.613475787,"remaining_time":1.24896405},
{"learn":[0.3561336517],"iteration":818,"passed_time":5.619153173,"remaining_time":1.241839712},
{"learn":[0.356044576],"iteration":819,"passed_time":5.625052971,"remaining_time":1.234767725},
{"learn":[0.3559665833],"iteration":820,"passed_time":5.6315703,"remaining_time":1.227833232},
{"learn":[0.3558993378],"iteration":821,"passed_time":5.637494224,"remaining_time":1.220771255},
{"learn":[0.3558195343],"iteration":822,"passed_time":5.64254104,"remaining_time":1.213523407},
{"learn":[0.3557648773],"iteration":823,"passed_time":5.647497941,"remaining_time":1.206261696},
{"learn":[0.3556885071],"iteration":824,"passed_time":5.653980854,"remaining_time":1.199329272},
{"learn":[0.355605779],"iteration":825,"passed_time":5.658815883,"remaining_time":1.192050803},
{"learn":[0.3555472921],"iteration":826,"passed_time":5.664313606,"remaining_time":1.184916873},
{"learn":[0.3554787852],"iteration":827,"passed_time":5.669741123,"remaining_time":1.17777231},
{"learn":[0.3553934123],"iteration":828,"passed_time":5.675052475,"remaining_time":1.170607929},
{"learn":[0.3553220011],"iteration":829,"passed_time":5.679938544,"remaining_time":1.163360907},
{"learn":[0.3552414551],"iteration":830,"passed_time":5.685707096,"remaining_time":1.156299036},
{"learn":[0.3551865031],"iteration":831,"passed_time":5.690586165,"remaining_time":1.149060668},
{"learn":[0.3551013387],"iteration":832,"passed_time":5.695307195,"remaining_time":1.14179628},
{"learn":[0.3550243327],"iteration":833,"passed_time":5.700699755,"remaining_time":1.134671654},
{"learn":[0.3549539846],"iteration":834,"passed_time":5.705746696,"remaining_time":1.12748288},
{"learn":[0.3548547821],"iteration":835,"passed_time":5.71181645,"remaining_time":1.120499878},
{"learn":[0.3547642263],"iteration":836,"passed_time":5.717326256,"remaining_time":1.113410012},
{"learn":[0.3547057037],"iteration":837,"passed_time":5.722050037,"remaining_time":1.106171964},
{"learn":[0.3546429647],"iteration":838,"passed_time":5.727452512,"remaining_time":1.099070148},
{"learn":[0.3545441284],"iteration":839,"passed_time":5.732624034,"remaining_time":1.091928387},
{"learn":[0.3544703115],"iteration":840,"passed_time":5.737505103,"remaining_time":1.084736399},
{"learn":[0.354434845],"iteration":841,"passed_time":5.742499753,"remaining_time":1.077571213},
{"learn":[0.3543504842],"iteration":842,"passed_time":5.747181493,"remaining_time":1.0703529},
{"learn":[0.3543060862],"iteration":843,"passed_time":5.752327181,"remaining_time":1.063226351},
{"learn":[0.3541983439],"iteration":844,"passed_time":5.757631575,"remaining_time":1.056133603},
{"learn":[0.3541176402],"iteration":845,"passed_time":5.763574957,"remaining_time":1.049161399},
{"learn":[0.3540526225],"iteration":846,"passed_time":5.769328134,"remaining_time":1.042157266},
{"learn":[0.3539828084],"iteration":847,"passed_time":5.774271993,"remaining_time":1.035011018},
{"learn":[0.3539390004],"iteration":848,"passed_time":5.779165438,"remaining_time":1.027860991},
{"learn":[0.3538753459],"iteration":849,"passed_time":5.785361522,"remaining_time":1.020946151},
{"learn":[0.3537717539],"iteration":850,"passed_time":5.791174364,"remaining_time":1.013965899},
{"learn":[0.3536777649],"iteration":851,"passed_time":5.795585318,"remaining_time":1.006744867},
{"learn":[0.3536001027],"iteration":852,"passed_time":5.80083538,"remaining_time":0.9996750303},
{"learn":[0.3535144246],"iteration":853,"passed_time":5.805991986,"remaining_time":0.9925934777},
{"learn":[0.3534498037],"iteration":854,"passed_time":5.811525626,"remaining_time":0.9855803693},
{"learn":[0.3533743795],"iteration":855,"passed_time":5.816383237,"remaining_time":0.9784569931},
{"learn":[0.3532563019],"iteration":856,"passed_time":5.820944563,"remaining_time":0.9712894661},
{"learn":[0.3531702983],"iteration":857,"passed_time":5.826163959,"remaining_time":0.9642369255},
{"learn":[0.3530924937],"iteration":858,"passed_time":5.83157985,"remaining_time":0.9572209068},
{"learn":[0.3530425517],"iteration":859,"passed_time":5.836053719,"remaining_time":0.9500552566},
{"learn":[0.352995458],"iteration":860,"passed_time":5.847966439,"remaining_time":0.9440967887},
{"learn":[0.3529587351],"iteration":861,"passed_time":5.858606519,"remaining_time":0.9379207652},
{"learn":[0.352872289],"iteration":862,"passed_time":5.866155827,"remaining_time":0.9312437409},
{"learn":[0.3528022207],"iteration":863,"passed_time":5.873144563,"remaining_time":0.924476459},
{"learn":[0.352752238],"iteration":864,"passed_time":5.877886593,"remaining_time":0.9173580232},
{"learn":[0.3526931915],"iteration":865,"passed_time":5.882823953,"remaining_time":0.9102752998},
{"learn":[0.3525831197],"iteration":866,"passed_time":5.887478985,"remaining_time":0.9031542157},
{"learn":[0.3525205688],"iteration":867,"passed_time":5.892400762,"remaining_time":0.8960793785},
{"learn":[0.3524296977],"iteration":868,"passed_time":5.897524284,"remaining_time":0.8890399094},
{"learn":[0.3524010162],"iteration":869,"passed_time":5.903274586,"remaining_time":0.8820985013},
{"learn":[0.3523442739],"iteration":870,"passed_time":5.909378547,"remaining_time":0.8752122073},
{"learn":[0.3522644806],"iteration":871,"passed_time":5.915064392,"remaining_time":0.8682663328},
{"learn":[0.3521873983],"iteration":872,"passed_time":5.920454618,"remaining_time":0.8612803396},
{"learn":[0.3520872294],"iteration":873,"passed_time":5.926141254,"remaining_time":0.85434073},
{"learn":[0.3520182292],"iteration":874,"passed_time":5.931287984,"remaining_time":0.8473268549},
{"learn":[0.3520157166],"iteration":875,"passed_time":5.935541358,"remaining_time":0.8401907858},
{"learn":[0.3519512177],"iteration":876,"passed_time":5.940645423,"remaining_time":0.8331806009},
{"learn":[0.3519045563],"iteration":877,"passed_time":5.946044149,"remaining_time":0.8262157018},
{"learn":[0.3518400269],"iteration":878,"passed_time":5.951343418,"remaining_time":0.8192406753},
{"learn":[0.35178007],"iteration":879,"passed_time":5.956426942,"remaining_time":0.8122400375},
{"learn":[0.3517349091],"iteration":880,"passed_time":5.96195729,"remaining_time":0.8053041062},
{"learn":[0.3516523946],"iteration":881,"passed_time":5.966929399,"remaining_time":0.798296677},
{"learn":[0.3515927734],"iteration":882,"passed_time":5.971239771,"remaining_time":0.7912061758},
{"learn":[0.3514868317],"iteration":883,"passed_time":5.977291733,"remaining_time":0.7843504989},
{"learn":[0.3514190572],"iteration":884,"passed_time":5.982326508,"remaining_time":0.7773644615},
{"learn":[0.3513773651],"iteration":885,"passed_time":5.98713862,"remaining_time":0.7703541791},
{"learn":[0.3513226318],"iteration":886,"passed_time":5.992519929,"remaining_time":0.7634213664},
{"learn":[0.3512709351],"iteration":887,"passed_time":5.998343146,"remaining_time":0.7565477842},
{"learn":[0.351225886],"iteration":888,"passed_time":6.002794849,"remaining_time":0.7495053186},
{"learn":[0.3511873525],"iteration":889,"passed_time":6.007524713,"remaining_time":0.7425030544},
{"learn":[0.3511053111],"iteration":890,"passed_time":6.012004665,"remaining_time":0.7354753182},
{"learn":[0.3510742849],"iteration":891,"passed_time":6.016810736,"remaining_time":0.7284927796},
{"learn":[0.350986969],"iteration":892,"passed_time":6.022602661,"remaining_time":0.7216332416},
{"learn":[0.3509359741],"iteration":893,"passed_time":6.027356066,"remaining_time":0.7146529564},
{"learn":[0.350888031],"iteration":894,"passed_time":6.032097638,"remaining_time":0.7076762593},
{"learn":[0.3508000285],"iteration":895,"passed_time":6.037418865,"remaining_time":0.7007718326},
{"learn":[0.3507041982],"iteration":896,"passed_time":6.042479681,"remaining_time":0.6938410336},
{"learn":[0.3506111348],"iteration":897,"passed_time":6.047301169,"remaining_time":0.6868872152},
{"learn":[0.3505556081],"iteration":898,"passed_time":6.052197696,"remaining_time":0.679946571},
{"learn":[0.3504510295],"iteration":899,"passed_time":6.057242596,"remaining_time":0.6730269551},
{"learn":[0.350386795],"iteration":900,"passed_time":6.062463116,"remaining_time":0.6661307975},
{"learn":[0.3503528239],"iteration":901,"passed_time":6.067011276,"remaining_time":0.6591653049},
{"learn":[0.3502852071],"iteration":902,"passed_time":6.072379668,"remaining_time":0.6522932756},
{"learn":[0.3502339172],"iteration":903,"passed_time":6.077698396,"remaining_time":0.6454192987},
{"learn":[0.3501669668],"iteration":904,"passed_time":6.082551507,"remaining_time":0.638499882},
{"learn":[0.3501359049],"iteration":905,"passed_time":6.087402745,"remaining_time":0.6315848322},
{"learn":[0.3500972239],"iteration":906,"passed_time":6.091902613,"remaining_time":0.6246383054},
{"learn":[0.3500360565],"iteration":907,"passed_time":6.0966941,"remaining_time":0.617726715},
{"learn":[0.3499729309],"iteration":908,"passed_time":6.102960391,"remaining_time":0.6109674319},
{"learn":[0.3499148661],"iteration":909,"passed_time":6.108166995,"remaining_time":0.6041044281},
{"learn":[0.3498252157],"iteration":910,"passed_time":6.113178603,"remaining_time":0.5972260106},
{"learn":[0.3497727356],"iteration":911,"passed_time":6.118259377,"remaining_time":0.5903583609},
{"learn":[0.3497131907],"iteration":912,"passed_time":6.123820016,"remaining_time":0.583540352},
{"learn":[0.3496519368],"iteration":913,"passed_time":6.12899787,"remaining_time":0.5766890775},
{"learn":[0.3495848745],"iteration":914,"passed_time":6.133985062,"remaining_time":0.5698237489},
{"learn":[0.3495322723],"iteration":915,"passed_time":6.138757051,"remaining_time":0.5629427863},
{"learn":[0.3493964844],"iteration":916,"passed_time":6.144246816,"remaining_time":0.5561313912},
{"learn":[0.3493227234],"iteration":917,"passed_time":6.149128303,"remaining_time":0.5492685412},
{"learn":[0.349267512],"iteration":918,"passed_time":6.15352859,"remaining_time":0.5423675906},
{"learn":[0.3491751658],"iteration":919,"passed_time":6.159101271,"remaining_time":0.5355740235},
{"learn":[0.3491184438],"iteration":920,"passed_time":6.164314584,"remaining_time":0.5287522824},
{"learn":[0.3490193787],"iteration":921,"passed_time":6.169300776,"remaining_time":0.5219148162},
{"learn":[0.3489427185],"iteration":922,"passed_time":6.173964892,"remaining_time":0.5150544926},
{"learn":[0.3488540955],"iteration":923,"passed_time":6.178897711,"remaining_time":0.5082210238},
{"learn":[0.3487965851],"iteration":924,"passed_time":6.183866111,"remaining_time":0.5013945496},
{"learn":[0.3486982015],"iteration":925,"passed_time":6.18888497,"remaining_time":0.4945761207},
{"learn":[0.3485949402],"iteration":926,"passed_time":6.194111324,"remaining_time":0.4877779144},
{"learn":[0.3485205638],"iteration":927,"passed_time":6.199966373,"remaining_time":0.4810318738},
{"learn":[0.3484633331],"iteration":928,"passed_time":6.205199852,"remaining_time":0.474240247},
{"learn":[0.3483974355],"iteration":929,"passed_time":6.209947799,"remaining_time":0.4674154257},
{"learn":[0.3483166809],"iteration":930,"passed_time":6.214718745,"remaining_time":0.4605967705},
{"learn":[0.3482480672],"iteration":931,"passed_time":6.219628939,"remaining_time":0.4537926693},
{"learn":[0.34820224],"iteration":932,"passed_time":6.224931542,"remaining_time":0.4470208074},
{"learn":[0.3481133626],"iteration":933,"passed_time":6.229793362,"remaining_time":0.4402209442},
{"learn":[0.3480527344],"iteration":934,"passed_time":6.234946509,"remaining_time":0.4334454792},
{"learn":[0.3480158234],"iteration":935,"passed_time":6.239935284,"remaining_time":0.4266622417},
{"learn":[0.3479523061],"iteration":936,"passed_time":6.244545567,"remaining_time":0.4198573861},
{"learn":[0.3479068553],"iteration":937,"passed_time":6.249744964,"remaining_time":0.413096149},
{"learn":[0.3478319982],"iteration":938,"passed_time":6.254387704,"remaining_time":0.4063020766},
{"learn":[0.3477471517],"iteration":939,"passed_time":6.259067568,"remaining_time":0.3995149512},
{"learn":[0.3476734009],"iteration":940,"passed_time":6.263391315,"remaining_time":0.3927099762},
{"learn":[0.3476265564],"iteration":941,"passed_time":6.268314259,"remaining_time":0.3859471624},
{"learn":[0.3475272115],"iteration":942,"passed_time":6.275606821,"remaining_time":0.3793314834},
{"learn":[0.347430275],"iteration":943,"passed_time":6.28067022,"remaining_time":0.3725821317},
{"learn":[0.3473665263],"iteration":944,"passed_time":6.285738661,"remaining_time":0.3658366417},
{"learn":[0.3472987289],"iteration":945,"passed_time":6.290290737,"remaining_time":0.3590652218},
{"learn":[0.3471706797],"iteration":946,"passed_time":6.296500738,"remaining_time":0.3523912768},
{"learn":[0.3471420898],"iteration":947,"passed_time":6.302310497,"remaining_time":0.3456963564},
{"learn":[0.3471004791],"iteration":948,"passed_time":6.307529685,"remaining_time":0.3389715637},
{"learn":[0.3470693512],"iteration":949,"passed_time":6.313446317,"remaining_time":0.3322866483},
{"learn":[0.3470180689],"iteration":950,"passed_time":6.318090932,"remaining_time":0.3255378083},
{"learn":[0.3469508514],"iteration":951,"passed_time":6.32324758,"remaining_time":0.3188192057},
{"learn":[0.3469122009],"iteration":952,"passed_time":6.328979798,"remaining_time":0.3121322671},
{"learn":[0.3468290838],"iteration":953,"passed_time":6.333696662,"remaining_time":0.3053983715},
{"learn":[0.3467676748],"iteration":954,"passed_time":6.339376133,"remaining_time":0.2987140586},
{"learn":[0.3467066065],"iteration":955,"passed_time":6.344562154,"remaining_time":0.2920091368},
{"learn":[0.346604332],"iteration":956,"passed_time":6.349780134,"remaining_time":0.2853088252},
{"learn":[0.346523262],"iteration":957,"passed_time":6.354386458,"remaining_time":0.2785847925},
{"learn":[0.3464359919],"iteration":958,"passed_time":6.360029095,"remaining_time":0.2719094817},
{"learn":[0.3463345998],"iteration":959,"passed_time":6.364691461,"remaining_time":0.2651954776},
{"learn":[0.3462511953],"iteration":960,"passed_time":6.369745777,"remaining_time":0.2585016496},
{"learn":[0.3461926219],"iteration":961,"passed_time":6.375643617,"remaining_time":0.2518445504},
{"learn":[0.3460992203],"iteration":962,"passed_time":6.381016927,"remaining_time":0.2451688746},
{"learn":[0.3460738093],"iteration":963,"passed_time":6.386520734,"remaining_time":0.2385007743},
{"learn":[0.3459818573],"iteration":964,"passed_time":6.391835087,"remaining_time":0.2318282156},
{"learn":[0.345896581],"iteration":965,"passed_time":6.396823737,"remaining_time":0.2251470052},
{"learn":[0.3458358434],"iteration":966,"passed_time":6.401562975,"remaining_time":0.2184607841},
{"learn":[0.3458062032],"iteration":967,"passed_time":6.406613542,"remaining_time":0.2117888774},
{"learn":[0.3457375209],"iteration":968,"passed_time":6.411889978,"remaining_time":0.2051275432},
{"learn":[0.3456519038],"iteration":969,"passed_time":6.416332515,"remaining_time":0.1984432737},
{"learn":[0.3455643463],"iteration":970,"passed_time":6.421573035,"remaining_time":0.1917874542},
{"learn":[0.3454865646],"iteration":971,"passed_time":6.427388669,"remaining_time":0.1851511139},
{"learn":[0.3453918686],"iteration":972,"passed_time":6.432847602,"remaining_time":0.1785065624},
{"learn":[0.345318128],"iteration":973,"passed_time":6.437669798,"remaining_time":0.1718474484},
{"learn":[0.3452528229],"iteration":974,"passed_time":6.443992172,"remaining_time":0.1652305685},
{"learn":[0.3451771062],"iteration":975,"passed_time":6.448912698,"remaining_time":0.1585798205},
{"learn":[0.3450691783],"iteration":976,"passed_time":6.453920932,"remaining_time":0.151934679},
{"learn":[0.3450069122],"iteration":977,"passed_time":6.463017959,"remaining_time":0.1453848621},
{"learn":[0.3449349899],"iteration":978,"passed_time":6.46921646,"remaining_time":0.1387676667},
{"learn":[0.3448893305],"iteration":979,"passed_time":6.475984117,"remaining_time":0.1321629412},
{"learn":[0.3448099391],"iteration":980,"passed_time":6.480843395,"remaining_time":0.125520922},
{"learn":[0.3447506638],"iteration":981,"passed_time":6.48625312,"remaining_time":0.1188926234},
{"learn":[0.3446678899],"iteration":982,"passed_time":6.491692221,"remaining_time":0.1122673121},
{"learn":[0.3446177648],"iteration":983,"passed_time":6.496657205,"remaining_time":0.1056367025},
{"learn":[0.3445514679],"iteration":984,"passed_time":6.501704229,"remaining_time":0.0990107243},
{"learn":[0.3444635468],"iteration":985,"passed_time":6.506339261,"remaining_time":0.09238209905},
{"learn":[0.3444031779],"iteration":986,"passed_time":6.512537971,"remaining_time":0.08577810904},
{"learn":[0.3443674037],"iteration":987,"passed_time":6.519934114,"remaining_time":0.07918948317},
{"learn":[0.3443314056],"iteration":988,"passed_time":6.525701583,"remaining_time":0.07258110962},
{"learn":[0.3442680511],"iteration":989,"passed_time":6.530906188,"remaining_time":0.06596874937},
{"learn":[0.3441725006],"iteration":990,"passed_time":6.536196707,"remaining_time":0.05936001046},
{"learn":[0.3440624771],"iteration":991,"passed_time":6.541143401,"remaining_time":0.05275115646},
{"learn":[0.3439745509],"iteration":992,"passed_time":6.545848182,"remaining_time":0.04614394489},
{"learn":[0.3439334056],"iteration":993,"passed_time":6.550442423,"remaining_time":0.0395398939},
{"learn":[0.3438701909],"iteration":994,"passed_time":6.555611112,"remaining_time":0.03294276941},
{"learn":[0.343833341],"iteration":995,"passed_time":6.560556554,"remaining_time":0.02634761668},
{"learn":[0.3437558517],"iteration":996,"passed_time":6.565675869,"remaining_time":0.0197562965},
{"learn":[0.3436889547],"iteration":997,"passed_time":6.57066102,"remaining_time":0.01316765735},
{"learn":[0.3436511841],"iteration":998,"passed_time":6.575793834,"remaining_time":0.00658237621},
{"learn":[0.3435861715],"iteration":999,"passed_time":6.581267391,"remaining_time":0}
]}